{
"meta":{"test_sets":[],"test_metrics":[],"learn_metrics":[{"best_value":"Min","name":"Logloss"}],"launch_mode":"Train","parameters":"","iteration_count":1000,"learn_sets":["learn"],"name":"experiment"},
"iterations":[
{"learn":[0.666997992],"iteration":0,"passed_time":0.02639216333,"remaining_time":26.36577117},
{"learn":[0.6417648666],"iteration":1,"passed_time":0.04482005005,"remaining_time":22.36520498},
{"learn":[0.623656982],"iteration":2,"passed_time":0.06301223628,"remaining_time":20.94106652},
{"learn":[0.6019721127],"iteration":3,"passed_time":0.08170253093,"remaining_time":20.3439302},
{"learn":[0.5876340595],"iteration":4,"passed_time":0.09980859503,"remaining_time":19.86191041},
{"learn":[0.5714199484],"iteration":5,"passed_time":0.1158803935,"remaining_time":19.19751852},
{"learn":[0.559469622],"iteration":6,"passed_time":0.1311669264,"remaining_time":18.60696542},
{"learn":[0.5456675065],"iteration":7,"passed_time":0.1480513645,"remaining_time":18.3583692},
{"learn":[0.5325893535],"iteration":8,"passed_time":0.1647066435,"remaining_time":18.13603153},
{"learn":[0.5166675342],"iteration":9,"passed_time":0.1807907333,"remaining_time":17.89828259},
{"learn":[0.5054785777],"iteration":10,"passed_time":0.199137331,"remaining_time":17.9042564},
{"learn":[0.4967104662],"iteration":11,"passed_time":0.2178082513,"remaining_time":17.93287936},
{"learn":[0.4887377277],"iteration":12,"passed_time":0.2343527841,"remaining_time":17.79278445},
{"learn":[0.4811583754],"iteration":13,"passed_time":0.2531118681,"remaining_time":17.82630728},
{"learn":[0.4731301299],"iteration":14,"passed_time":0.2828882105,"remaining_time":18.57632582},
{"learn":[0.4651567735],"iteration":15,"passed_time":0.3064355518,"remaining_time":18.84578644},
{"learn":[0.4581444347],"iteration":16,"passed_time":0.3225111001,"remaining_time":18.64873008},
{"learn":[0.4519438043],"iteration":17,"passed_time":0.3360014428,"remaining_time":18.33074538},
{"learn":[0.4462890326],"iteration":18,"passed_time":0.3527123034,"remaining_time":18.21109314},
{"learn":[0.4416910249],"iteration":19,"passed_time":0.3664912198,"remaining_time":17.95806977},
{"learn":[0.4337212655],"iteration":20,"passed_time":0.3794834958,"remaining_time":17.69115916},
{"learn":[0.4285062897],"iteration":21,"passed_time":0.3933168687,"remaining_time":17.48472262},
{"learn":[0.4219993401],"iteration":22,"passed_time":0.4072546549,"remaining_time":17.29946947},
{"learn":[0.4184170039],"iteration":23,"passed_time":0.4277759302,"remaining_time":17.39622116},
{"learn":[0.4143191781],"iteration":24,"passed_time":0.4411139864,"remaining_time":17.20344547},
{"learn":[0.409335133],"iteration":25,"passed_time":0.4548520292,"remaining_time":17.03945678},
{"learn":[0.4059456948],"iteration":26,"passed_time":0.4688253975,"remaining_time":16.89507821},
{"learn":[0.4024317538],"iteration":27,"passed_time":0.4836563622,"remaining_time":16.78978515},
{"learn":[0.3986364821],"iteration":28,"passed_time":0.4996192893,"remaining_time":16.72863207},
{"learn":[0.3949627736],"iteration":29,"passed_time":0.5133314996,"remaining_time":16.59771849},
{"learn":[0.3919390647],"iteration":30,"passed_time":0.5258869151,"remaining_time":16.43820712},
{"learn":[0.3846617613],"iteration":31,"passed_time":0.5392847192,"remaining_time":16.31336276},
{"learn":[0.3799562618],"iteration":32,"passed_time":0.551690223,"remaining_time":16.16619532},
{"learn":[0.3773497172],"iteration":33,"passed_time":0.5646798324,"remaining_time":16.04355053},
{"learn":[0.3744795415],"iteration":34,"passed_time":0.5776319847,"remaining_time":15.92613901},
{"learn":[0.3672563642],"iteration":35,"passed_time":0.5911458266,"remaining_time":15.82957158},
{"learn":[0.3646448324],"iteration":36,"passed_time":0.6083734199,"remaining_time":15.83415144},
{"learn":[0.3623791881],"iteration":37,"passed_time":0.6282554249,"remaining_time":15.90478207},
{"learn":[0.360091174],"iteration":38,"passed_time":0.652212336,"remaining_time":16.07118089},
{"learn":[0.3580414909],"iteration":39,"passed_time":0.6755802666,"remaining_time":16.2139264},
{"learn":[0.3537942836],"iteration":40,"passed_time":0.6956884724,"remaining_time":16.27232305},
{"learn":[0.347717611],"iteration":41,"passed_time":0.7103112774,"remaining_time":16.201862},
{"learn":[0.3443531171],"iteration":42,"passed_time":0.7257217229,"remaining_time":16.15152765},
{"learn":[0.3415644388],"iteration":43,"passed_time":0.740501856,"remaining_time":16.08908578},
{"learn":[0.3377500246],"iteration":44,"passed_time":0.7564131182,"remaining_time":16.05276729},
{"learn":[0.3360308021],"iteration":45,"passed_time":0.7806643528,"remaining_time":16.19029984},
{"learn":[0.334339242],"iteration":46,"passed_time":0.8089328703,"remaining_time":16.4024048},
{"learn":[0.3324565883],"iteration":47,"passed_time":0.8291183235,"remaining_time":16.44418008},
{"learn":[0.3293169874],"iteration":48,"passed_time":0.8498857157,"remaining_time":16.49472073},
{"learn":[0.3278808517],"iteration":49,"passed_time":0.8700803353,"remaining_time":16.53152637},
{"learn":[0.3266089166],"iteration":50,"passed_time":0.8877544555,"remaining_time":16.51919565},
{"learn":[0.3239551686],"iteration":51,"passed_time":0.9046798922,"remaining_time":16.49301034},
{"learn":[0.3224892827],"iteration":52,"passed_time":0.9225787548,"remaining_time":16.48456756},
{"learn":[0.3206047797],"iteration":53,"passed_time":1.096621296,"remaining_time":19.21118048},
{"learn":[0.3151950199],"iteration":54,"passed_time":1.182805386,"remaining_time":20.32274709},
{"learn":[0.3114956891],"iteration":55,"passed_time":1.215268389,"remaining_time":20.48595284},
{"learn":[0.3077966946],"iteration":56,"passed_time":1.242089413,"remaining_time":20.54895292},
{"learn":[0.3062502877],"iteration":57,"passed_time":1.26792722,"remaining_time":20.59288692},
{"learn":[0.3039547178],"iteration":58,"passed_time":1.290762877,"remaining_time":20.58657402},
{"learn":[0.3017196052],"iteration":59,"passed_time":1.309094558,"remaining_time":20.50914808},
{"learn":[0.3004605813],"iteration":60,"passed_time":1.325818002,"remaining_time":20.40890334},
{"learn":[0.2991181974],"iteration":61,"passed_time":1.342107335,"remaining_time":20.30478516},
{"learn":[0.2978079044],"iteration":62,"passed_time":1.359386301,"remaining_time":20.21817403},
{"learn":[0.2966923446],"iteration":63,"passed_time":1.375157693,"remaining_time":20.11168126},
{"learn":[0.2932359127],"iteration":64,"passed_time":1.392952476,"remaining_time":20.03708561},
{"learn":[0.2919848275],"iteration":65,"passed_time":1.407576031,"remaining_time":19.91933353},
{"learn":[0.2895526865],"iteration":66,"passed_time":1.421674228,"remaining_time":19.7973441},
{"learn":[0.2883170625],"iteration":67,"passed_time":1.437690737,"remaining_time":19.7048201},
{"learn":[0.2873393112],"iteration":68,"passed_time":1.454665755,"remaining_time":19.62744664},
{"learn":[0.2862225839],"iteration":69,"passed_time":1.470202572,"remaining_time":19.53269131},
{"learn":[0.2852387824],"iteration":70,"passed_time":1.48814185,"remaining_time":19.47160251},
{"learn":[0.2802227552],"iteration":71,"passed_time":1.503368384,"remaining_time":19.37674807},
{"learn":[0.2775915409],"iteration":72,"passed_time":1.520188575,"remaining_time":19.30431245},
{"learn":[0.2767972181],"iteration":73,"passed_time":1.535510356,"remaining_time":19.2146296},
{"learn":[0.2758259748],"iteration":74,"passed_time":1.550398278,"remaining_time":19.12157876},
{"learn":[0.2747799874],"iteration":75,"passed_time":1.567723576,"remaining_time":19.06021821},
{"learn":[0.273849783],"iteration":76,"passed_time":1.584315982,"remaining_time":18.99121625},
{"learn":[0.2722247861],"iteration":77,"passed_time":1.601315375,"remaining_time":18.92836892},
{"learn":[0.2688053692],"iteration":78,"passed_time":1.619515019,"remaining_time":18.8806751},
{"learn":[0.2679529088],"iteration":79,"passed_time":1.634695931,"remaining_time":18.7990032},
{"learn":[0.2671972209],"iteration":80,"passed_time":1.65073848,"remaining_time":18.72874893},
{"learn":[0.2661439942],"iteration":81,"passed_time":1.667631709,"remaining_time":18.66934036},
{"learn":[0.2654257161],"iteration":82,"passed_time":1.683565512,"remaining_time":18.60035632},
{"learn":[0.2638478219],"iteration":83,"passed_time":1.69906783,"remaining_time":18.52793014},
{"learn":[0.2630043224],"iteration":84,"passed_time":1.716398545,"remaining_time":18.47652551},
{"learn":[0.262257024],"iteration":85,"passed_time":1.732000692,"remaining_time":18.40754224},
{"learn":[0.2599734091],"iteration":86,"passed_time":1.751648372,"remaining_time":18.38224096},
{"learn":[0.2591119367],"iteration":87,"passed_time":1.768711762,"remaining_time":18.33028553},
{"learn":[0.2575793242],"iteration":88,"passed_time":1.787137857,"remaining_time":18.29306279},
{"learn":[0.2567222737],"iteration":89,"passed_time":1.800865817,"remaining_time":18.20875437},
{"learn":[0.2558995116],"iteration":90,"passed_time":1.816754872,"remaining_time":18.14758438},
{"learn":[0.255152064],"iteration":91,"passed_time":1.831379802,"remaining_time":18.07492239},
{"learn":[0.252624894],"iteration":92,"passed_time":1.846411885,"remaining_time":18.00747935},
{"learn":[0.2519304213],"iteration":93,"passed_time":1.862269065,"remaining_time":17.94910397},
{"learn":[0.249463261],"iteration":94,"passed_time":1.878696268,"remaining_time":17.89705393},
{"learn":[0.248910754],"iteration":95,"passed_time":1.894309957,"remaining_time":17.83808543},
{"learn":[0.2482350399],"iteration":96,"passed_time":1.909116464,"remaining_time":17.77249657},
{"learn":[0.2467970347],"iteration":97,"passed_time":1.923588358,"remaining_time":17.70486427},
{"learn":[0.2461871515],"iteration":98,"passed_time":1.938433572,"remaining_time":17.64170352},
{"learn":[0.2452601169],"iteration":99,"passed_time":1.955905741,"remaining_time":17.60315167},
{"learn":[0.244438586],"iteration":100,"passed_time":1.971321728,"remaining_time":17.54671518},
{"learn":[0.2437623373],"iteration":101,"passed_time":1.985832036,"remaining_time":17.4831095},
{"learn":[0.2432358735],"iteration":102,"passed_time":2.003522739,"remaining_time":17.44815434},
{"learn":[0.2426023632],"iteration":103,"passed_time":2.018050422,"remaining_time":17.38628056},
{"learn":[0.2407613382],"iteration":104,"passed_time":2.033610405,"remaining_time":17.33410773},
{"learn":[0.2402261014],"iteration":105,"passed_time":2.047887054,"remaining_time":17.27180214},
{"learn":[0.2390244857],"iteration":106,"passed_time":2.063270001,"remaining_time":17.2196272},
{"learn":[0.2385219218],"iteration":107,"passed_time":2.078617323,"remaining_time":17.16783938},
{"learn":[0.2360616738],"iteration":108,"passed_time":2.094476921,"remaining_time":17.12090767},
{"learn":[0.2353630262],"iteration":109,"passed_time":2.11026702,"remaining_time":17.07397862},
{"learn":[0.2348829729],"iteration":110,"passed_time":2.125494305,"remaining_time":17.02310304},
{"learn":[0.2334141366],"iteration":111,"passed_time":2.141912675,"remaining_time":16.98230764},
{"learn":[0.2328727823],"iteration":112,"passed_time":2.158580412,"remaining_time":16.94390111},
{"learn":[0.2317067567],"iteration":113,"passed_time":2.177353412,"remaining_time":16.92223793},
{"learn":[0.2305276505],"iteration":114,"passed_time":2.193608997,"remaining_time":16.88125184},
{"learn":[0.2293766418],"iteration":115,"passed_time":2.20967192,"remaining_time":16.83922394},
{"learn":[0.228803408],"iteration":116,"passed_time":2.224900955,"remaining_time":16.79134652},
{"learn":[0.2275346528],"iteration":117,"passed_time":2.240814634,"remaining_time":16.74913989},
{"learn":[0.2257660582],"iteration":118,"passed_time":2.256638191,"remaining_time":16.70670795},
{"learn":[0.2238530828],"iteration":119,"passed_time":2.27199268,"remaining_time":16.66127965},
{"learn":[0.2229654705],"iteration":120,"passed_time":2.289363185,"remaining_time":16.63099371},
{"learn":[0.2224090585],"iteration":121,"passed_time":2.304437641,"remaining_time":16.58439549},
{"learn":[0.2219143119],"iteration":122,"passed_time":2.318962866,"remaining_time":16.53439377},
{"learn":[0.2213516493],"iteration":123,"passed_time":2.332177635,"remaining_time":16.47570652},
{"learn":[0.2208755887],"iteration":124,"passed_time":2.347430877,"remaining_time":16.43201614},
{"learn":[0.220493567],"iteration":125,"passed_time":2.364258026,"remaining_time":16.39969456},
{"learn":[0.2199674026],"iteration":126,"passed_time":2.383731794,"remaining_time":16.38580989},
{"learn":[0.2193555402],"iteration":127,"passed_time":2.401009303,"remaining_time":16.35687587},
{"learn":[0.2189297893],"iteration":128,"passed_time":2.415463363,"remaining_time":16.30905883},
{"learn":[0.2184011106],"iteration":129,"passed_time":2.430615359,"remaining_time":16.26642586},
{"learn":[0.2173474925],"iteration":130,"passed_time":2.447895409,"remaining_time":16.23832909},
{"learn":[0.2168985431],"iteration":131,"passed_time":2.464321862,"remaining_time":16.20478315},
{"learn":[0.2155437909],"iteration":132,"passed_time":2.481977608,"remaining_time":16.17950817},
{"learn":[0.2149288639],"iteration":133,"passed_time":2.497182935,"remaining_time":16.13851061},
{"learn":[0.2130015],"iteration":134,"passed_time":2.512559965,"remaining_time":16.09899533},
{"learn":[0.212446337],"iteration":135,"passed_time":2.529112664,"remaining_time":16.06730398},
{"learn":[0.2112689411],"iteration":136,"passed_time":2.543543851,"remaining_time":16.02246966},
{"learn":[0.210708179],"iteration":137,"passed_time":2.558241362,"remaining_time":15.97973952},
{"learn":[0.210343321],"iteration":138,"passed_time":2.574195247,"remaining_time":15.94519502},
{"learn":[0.2098999041],"iteration":139,"passed_time":2.590995938,"remaining_time":15.91611791},
{"learn":[0.2096437857],"iteration":140,"passed_time":2.606919533,"remaining_time":15.88187148},
{"learn":[0.2090677584],"iteration":141,"passed_time":2.621569962,"remaining_time":15.84019034},
{"learn":[0.2080449202],"iteration":142,"passed_time":2.637078279,"remaining_time":15.80402857},
{"learn":[0.2069509055],"iteration":143,"passed_time":2.651883662,"remaining_time":15.7639751},
{"learn":[0.2064971457],"iteration":144,"passed_time":2.66620406,"remaining_time":15.72141015},
{"learn":[0.2059501881],"iteration":145,"passed_time":2.680709952,"remaining_time":15.68031712},
{"learn":[0.2054511391],"iteration":146,"passed_time":2.694813191,"remaining_time":15.63724934},
{"learn":[0.2050709408],"iteration":147,"passed_time":2.709892898,"remaining_time":15.60019425},
{"learn":[0.2045131591],"iteration":148,"passed_time":2.725914281,"remaining_time":15.56881244},
{"learn":[0.2040759933],"iteration":149,"passed_time":2.739559619,"remaining_time":15.52417117},
{"learn":[0.2031711611],"iteration":150,"passed_time":2.754194798,"remaining_time":15.48550585},
{"learn":[0.2020064898],"iteration":151,"passed_time":2.768979223,"remaining_time":15.44798935},
{"learn":[0.2012367157],"iteration":152,"passed_time":2.783063754,"remaining_time":15.40689542},
{"learn":[0.2008412611],"iteration":153,"passed_time":2.797699059,"remaining_time":15.36917795},
{"learn":[0.1999880681],"iteration":154,"passed_time":2.812165661,"remaining_time":15.3308386},
{"learn":[0.199557929],"iteration":155,"passed_time":2.825959035,"remaining_time":15.28916299},
{"learn":[0.1988476113],"iteration":156,"passed_time":2.839262592,"remaining_time":15.24521252},
{"learn":[0.1982659601],"iteration":157,"passed_time":2.85279585,"remaining_time":15.20287409},
{"learn":[0.1977722508],"iteration":158,"passed_time":2.868700071,"remaining_time":15.17343874},
{"learn":[0.1974665854],"iteration":159,"passed_time":2.881994587,"remaining_time":15.13047158},
{"learn":[0.1971585273],"iteration":160,"passed_time":2.895016904,"remaining_time":15.08645455},
{"learn":[0.1966908454],"iteration":161,"passed_time":2.908978689,"remaining_time":15.04767988},
{"learn":[0.1961761916],"iteration":162,"passed_time":2.923533538,"remaining_time":15.01225504},
{"learn":[0.1958354279],"iteration":163,"passed_time":2.937347037,"remaining_time":14.97330563},
{"learn":[0.1954211968],"iteration":164,"passed_time":2.950537806,"remaining_time":14.9315095},
{"learn":[0.1943529678],"iteration":165,"passed_time":2.962914602,"remaining_time":14.88596854},
{"learn":[0.1940504535],"iteration":166,"passed_time":2.976189494,"remaining_time":14.84530448},
{"learn":[0.1937307862],"iteration":167,"passed_time":2.988943444,"remaining_time":14.80238658},
{"learn":[0.1934180817],"iteration":168,"passed_time":3.001791892,"remaining_time":14.76029031},
{"learn":[0.1931190105],"iteration":169,"passed_time":3.016095957,"remaining_time":14.72564497},
{"learn":[0.1927223863],"iteration":170,"passed_time":3.030565643,"remaining_time":14.69204045},
{"learn":[0.192348468],"iteration":171,"passed_time":3.044091192,"remaining_time":14.65411341},
{"learn":[0.1920618931],"iteration":172,"passed_time":3.057750696,"remaining_time":14.61710882},
{"learn":[0.1915636558],"iteration":173,"passed_time":3.073719165,"remaining_time":14.59133351},
{"learn":[0.1912598948],"iteration":174,"passed_time":3.087307337,"remaining_time":14.55444888},
{"learn":[0.1908248499],"iteration":175,"passed_time":3.102053222,"remaining_time":14.52324917},
{"learn":[0.1901583828],"iteration":176,"passed_time":3.11651999,"remaining_time":14.49093758},
{"learn":[0.1898584334],"iteration":177,"passed_time":3.130248783,"remaining_time":14.45541854},
{"learn":[0.1884675898],"iteration":178,"passed_time":3.146742776,"remaining_time":14.43282581},
{"learn":[0.1880842964],"iteration":179,"passed_time":3.169791051,"remaining_time":14.44015923},
{"learn":[0.1876703021],"iteration":180,"passed_time":3.186016844,"remaining_time":14.41628616},
{"learn":[0.1874480021],"iteration":181,"passed_time":3.201683323,"remaining_time":14.38998329},
{"learn":[0.1866110856],"iteration":182,"passed_time":3.218915999,"remaining_time":14.37078891},
{"learn":[0.1859770725],"iteration":183,"passed_time":3.235200374,"remaining_time":14.34741035},
{"learn":[0.1850376173],"iteration":184,"passed_time":3.250471699,"remaining_time":14.31964559},
{"learn":[0.1847508502],"iteration":185,"passed_time":3.264559772,"remaining_time":14.28683685},
{"learn":[0.1842950354],"iteration":186,"passed_time":3.284149078,"remaining_time":14.27814546},
{"learn":[0.1840045096],"iteration":187,"passed_time":3.300383621,"remaining_time":14.25484841},
{"learn":[0.1836904497],"iteration":188,"passed_time":3.317393764,"remaining_time":14.23495419},
{"learn":[0.1833481749],"iteration":189,"passed_time":3.334365615,"remaining_time":14.2149271},
{"learn":[0.1826411079],"iteration":190,"passed_time":3.350314001,"remaining_time":14.190597},
{"learn":[0.181726117],"iteration":191,"passed_time":3.366762704,"remaining_time":14.16845971},
{"learn":[0.1802731802],"iteration":192,"passed_time":3.383782762,"remaining_time":14.14877041},
{"learn":[0.1799524159],"iteration":193,"passed_time":3.401022647,"remaining_time":14.13002193},
{"learn":[0.1796326762],"iteration":194,"passed_time":3.417315563,"remaining_time":14.10737963},
{"learn":[0.1792832916],"iteration":195,"passed_time":3.434672819,"remaining_time":14.08916809},
{"learn":[0.1789907788],"iteration":196,"passed_time":3.452861422,"remaining_time":14.07435392},
{"learn":[0.1787616226],"iteration":197,"passed_time":3.468323241,"remaining_time":14.0484608},
{"learn":[0.1784779604],"iteration":198,"passed_time":3.48401801,"remaining_time":14.02361018},
{"learn":[0.1778436961],"iteration":199,"passed_time":3.497907839,"remaining_time":13.99163136},
{"learn":[0.1775597631],"iteration":200,"passed_time":3.512054994,"remaining_time":13.96085542},
{"learn":[0.1770190742],"iteration":201,"passed_time":3.525148516,"remaining_time":13.92608176},
{"learn":[0.1766909105],"iteration":202,"passed_time":3.539707198,"remaining_time":13.89727407},
{"learn":[0.1763692548],"iteration":203,"passed_time":3.553096253,"remaining_time":13.86404224},
{"learn":[0.1761098567],"iteration":204,"passed_time":3.567238782,"remaining_time":13.83392601},
{"learn":[0.1759014719],"iteration":205,"passed_time":3.580994324,"remaining_time":13.80247327},
{"learn":[0.175705701],"iteration":206,"passed_time":3.594836405,"remaining_time":13.77152304},
{"learn":[0.1754905252],"iteration":207,"passed_time":3.608288166,"remaining_time":13.73925109},
{"learn":[0.1753021619],"iteration":208,"passed_time":3.621649263,"remaining_time":13.70681611},
{"learn":[0.1748598701],"iteration":209,"passed_time":3.635265726,"remaining_time":13.67552345},
{"learn":[0.1742490443],"iteration":210,"passed_time":3.649616457,"remaining_time":13.647144},
{"learn":[0.1740001054],"iteration":211,"passed_time":3.664363675,"remaining_time":13.62037064},
{"learn":[0.1737087897],"iteration":212,"passed_time":3.679436756,"remaining_time":13.59491421},
{"learn":[0.1733902319],"iteration":213,"passed_time":3.694898658,"remaining_time":13.57098292},
{"learn":[0.1732375947],"iteration":214,"passed_time":3.710013947,"remaining_time":13.54586488},
{"learn":[0.1728322548],"iteration":215,"passed_time":3.729390052,"remaining_time":13.53630463},
{"learn":[0.1726348459],"iteration":216,"passed_time":3.746722809,"remaining_time":13.51928092},
{"learn":[0.1723946205],"iteration":217,"passed_time":3.76486308,"remaining_time":13.50515105},
{"learn":[0.172181845],"iteration":218,"passed_time":3.78814768,"remaining_time":13.50933031},
{"learn":[0.171628876],"iteration":219,"passed_time":3.807201379,"remaining_time":13.49825944},
{"learn":[0.1713926901],"iteration":220,"passed_time":3.824658298,"remaining_time":13.48148785},
{"learn":[0.1711631228],"iteration":221,"passed_time":3.842513038,"remaining_time":13.46610425},
{"learn":[0.1709217736],"iteration":222,"passed_time":3.858862868,"remaining_time":13.44545493},
{"learn":[0.1705600072],"iteration":223,"passed_time":3.875889677,"remaining_time":13.42718924},
{"learn":[0.1700357057],"iteration":224,"passed_time":3.891353079,"remaining_time":13.40354949},
{"learn":[0.1696797995],"iteration":225,"passed_time":3.908517508,"remaining_time":13.38580775},
{"learn":[0.1693268605],"iteration":226,"passed_time":3.924792924,"remaining_time":13.36504375},
{"learn":[0.169037644],"iteration":227,"passed_time":3.942463336,"remaining_time":13.34904252},
{"learn":[0.1688719593],"iteration":228,"passed_time":3.958617924,"remaining_time":13.32792323},
{"learn":[0.1686432832],"iteration":229,"passed_time":3.976777694,"remaining_time":13.31356011},
{"learn":[0.1684125696],"iteration":230,"passed_time":3.992977322,"remaining_time":13.29263879},
{"learn":[0.1682042425],"iteration":231,"passed_time":4.00725143,"remaining_time":13.26538404},
{"learn":[0.1679655919],"iteration":232,"passed_time":4.02487051,"remaining_time":13.24925185},
{"learn":[0.1677138061],"iteration":233,"passed_time":4.04347235,"remaining_time":13.23632402},
{"learn":[0.1671087235],"iteration":234,"passed_time":4.062215767,"remaining_time":13.22380877},
{"learn":[0.1668240802],"iteration":235,"passed_time":4.080444077,"remaining_time":13.2095732},
{"learn":[0.1665502265],"iteration":236,"passed_time":4.097006526,"remaining_time":13.18994084},
{"learn":[0.1659651388],"iteration":237,"passed_time":4.110741403,"remaining_time":13.1612813},
{"learn":[0.1657787196],"iteration":238,"passed_time":4.126368882,"remaining_time":13.13877289},
{"learn":[0.1654896697],"iteration":239,"passed_time":4.143203406,"remaining_time":13.12014412},
{"learn":[0.1652569036],"iteration":240,"passed_time":4.158239322,"remaining_time":13.09586575},
{"learn":[0.1649849904],"iteration":241,"passed_time":4.173367235,"remaining_time":13.07195192},
{"learn":[0.164824787],"iteration":242,"passed_time":4.186267264,"remaining_time":13.04117004},
{"learn":[0.1645743987],"iteration":243,"passed_time":4.20089986,"remaining_time":13.01590285},
{"learn":[0.1642115346],"iteration":244,"passed_time":4.215140136,"remaining_time":12.98951348},
{"learn":[0.1629346404],"iteration":245,"passed_time":4.230277383,"remaining_time":12.96597214},
{"learn":[0.1624842232],"iteration":246,"passed_time":4.245126347,"remaining_time":12.94162},
{"learn":[0.161731071],"iteration":247,"passed_time":4.259615323,"remaining_time":12.91625291},
{"learn":[0.1615167241],"iteration":248,"passed_time":4.273523027,"remaining_time":12.88922005},
{"learn":[0.1612967258],"iteration":249,"passed_time":4.286478804,"remaining_time":12.85943641},
{"learn":[0.1611571197],"iteration":250,"passed_time":4.300830826,"remaining_time":12.83395334},
{"learn":[0.1609985946],"iteration":251,"passed_time":4.313940723,"remaining_time":12.80487167},
{"learn":[0.1608010212],"iteration":252,"passed_time":4.3264086,"remaining_time":12.77402065},
{"learn":[0.1605529096],"iteration":253,"passed_time":4.341060737,"remaining_time":12.74972957},
{"learn":[0.1602504374],"iteration":254,"passed_time":4.355527256,"remaining_time":12.72497179},
{"learn":[0.1600550444],"iteration":255,"passed_time":4.368971934,"remaining_time":12.69732468},
{"learn":[0.159818407],"iteration":256,"passed_time":4.38200675,"remaining_time":12.66860317},
{"learn":[0.1595427329],"iteration":257,"passed_time":4.396478726,"remaining_time":12.64413649},
{"learn":[0.1593225549],"iteration":258,"passed_time":4.409127181,"remaining_time":12.61452989},
{"learn":[0.158504647],"iteration":259,"passed_time":4.427647606,"remaining_time":12.60176626},
{"learn":[0.1581948837],"iteration":260,"passed_time":4.443917939,"remaining_time":12.58258758},
{"learn":[0.1577048134],"iteration":261,"passed_time":4.456909549,"remaining_time":12.5541956},
{"learn":[0.1574267448],"iteration":262,"passed_time":4.470275937,"remaining_time":12.52697097},
{"learn":[0.1571956667],"iteration":263,"passed_time":4.48331567,"remaining_time":12.49894066},
{"learn":[0.1569202011],"iteration":264,"passed_time":4.495057571,"remaining_time":12.46742383},
{"learn":[0.1564882158],"iteration":265,"passed_time":4.509121894,"remaining_time":12.44246417},
{"learn":[0.1559858374],"iteration":266,"passed_time":4.523025682,"remaining_time":12.41714541},
{"learn":[0.1557558603],"iteration":267,"passed_time":4.536295532,"remaining_time":12.39018033},
{"learn":[0.1552520425],"iteration":268,"passed_time":4.549661379,"remaining_time":12.36357795},
{"learn":[0.1550623507],"iteration":269,"passed_time":4.562749485,"remaining_time":12.33632268},
{"learn":[0.1548759417],"iteration":270,"passed_time":4.574336099,"remaining_time":12.3051329},
{"learn":[0.1545518832],"iteration":271,"passed_time":4.587266877,"remaining_time":12.27768488},
{"learn":[0.1543960638],"iteration":272,"passed_time":4.600926881,"remaining_time":12.25228514},
{"learn":[0.1541421388],"iteration":273,"passed_time":4.613866908,"remaining_time":12.22506341},
{"learn":[0.1538978006],"iteration":274,"passed_time":4.625987505,"remaining_time":12.19578524},
{"learn":[0.1536244181],"iteration":275,"passed_time":4.639179524,"remaining_time":12.16944194},
{"learn":[0.1534081294],"iteration":276,"passed_time":4.651441533,"remaining_time":12.14076617},
{"learn":[0.1531896203],"iteration":277,"passed_time":4.66326264,"remaining_time":12.1110634},
{"learn":[0.1527841636],"iteration":278,"passed_time":4.676729816,"remaining_time":12.08574264},
{"learn":[0.1525987506],"iteration":279,"passed_time":4.688878995,"remaining_time":12.05711742},
{"learn":[0.1524041402],"iteration":280,"passed_time":4.701326539,"remaining_time":12.02937289},
{"learn":[0.1522327013],"iteration":281,"passed_time":4.713353139,"remaining_time":12.00066508},
{"learn":[0.1518300521],"iteration":282,"passed_time":4.726117298,"remaining_time":11.97394383},
{"learn":[0.1513169316],"iteration":283,"passed_time":4.739570767,"remaining_time":11.94905869},
{"learn":[0.1510112986],"iteration":284,"passed_time":4.75272912,"remaining_time":11.92351341},
{"learn":[0.1507877072],"iteration":285,"passed_time":4.766102342,"remaining_time":11.89859116},
{"learn":[0.1502610823],"iteration":286,"passed_time":4.778816377,"remaining_time":11.87211177},
{"learn":[0.1500775974],"iteration":287,"passed_time":4.792829036,"remaining_time":11.84893845},
{"learn":[0.1499203097],"iteration":288,"passed_time":4.804632185,"remaining_time":11.82039268},
{"learn":[0.1497385402],"iteration":289,"passed_time":4.816650493,"remaining_time":11.79248914},
{"learn":[0.1489045216],"iteration":290,"passed_time":4.831360337,"remaining_time":11.7712525},
{"learn":[0.1486971278],"iteration":291,"passed_time":4.844250158,"remaining_time":11.74564764},
{"learn":[0.1484013803],"iteration":292,"passed_time":4.856831239,"remaining_time":11.71938459},
{"learn":[0.1482034211],"iteration":293,"passed_time":4.869322282,"remaining_time":11.6929984},
{"learn":[0.1474846876],"iteration":294,"passed_time":4.881704536,"remaining_time":11.66644643},
{"learn":[0.1470724701],"iteration":295,"passed_time":4.894319533,"remaining_time":11.64054375},
{"learn":[0.1468399294],"iteration":296,"passed_time":4.906389132,"remaining_time":11.61343959},
{"learn":[0.1465231986],"iteration":297,"passed_time":4.920362875,"remaining_time":11.59092194},
{"learn":[0.146237536],"iteration":298,"passed_time":4.932537345,"remaining_time":11.56424307},
{"learn":[0.1460143653],"iteration":299,"passed_time":4.945847527,"remaining_time":11.5403109},
{"learn":[0.1458473349],"iteration":300,"passed_time":4.957688508,"remaining_time":11.51303743},
{"learn":[0.1456571303],"iteration":301,"passed_time":4.971166851,"remaining_time":11.48965054},
{"learn":[0.1454896529],"iteration":302,"passed_time":4.986575088,"remaining_time":11.47076844},
{"learn":[0.1453034336],"iteration":303,"passed_time":5.00244531,"remaining_time":11.45296689},
{"learn":[0.1451697829],"iteration":304,"passed_time":5.015015933,"remaining_time":11.42765926},
{"learn":[0.1449677751],"iteration":305,"passed_time":5.030885822,"remaining_time":11.40991752},
{"learn":[0.1447285254],"iteration":306,"passed_time":5.045737202,"remaining_time":11.38988886},
{"learn":[0.144169639],"iteration":307,"passed_time":5.063149206,"remaining_time":11.37564692},
{"learn":[0.1439779499],"iteration":308,"passed_time":5.079417373,"remaining_time":11.35882655},
{"learn":[0.1436503739],"iteration":309,"passed_time":5.095738913,"remaining_time":11.34212855},
{"learn":[0.1433962131],"iteration":310,"passed_time":5.109969148,"remaining_time":11.32079982},
{"learn":[0.1432482304],"iteration":311,"passed_time":5.122925009,"remaining_time":11.29670643},
{"learn":[0.1429963386],"iteration":312,"passed_time":5.13630773,"remaining_time":11.27362112},
{"learn":[0.1426182755],"iteration":313,"passed_time":5.150149186,"remaining_time":11.25159981},
{"learn":[0.1425327728],"iteration":314,"passed_time":5.163235709,"remaining_time":11.22798876},
{"learn":[0.1423257031],"iteration":315,"passed_time":5.17992657,"remaining_time":11.21224612},
{"learn":[0.1420710714],"iteration":316,"passed_time":5.198107798,"remaining_time":11.1997086},
{"learn":[0.1418510688],"iteration":317,"passed_time":5.214629248,"remaining_time":11.18357594},
{"learn":[0.1416386126],"iteration":318,"passed_time":5.227707688,"remaining_time":11.16009071},
{"learn":[0.141139393],"iteration":319,"passed_time":5.241870758,"remaining_time":11.13897536},
{"learn":[0.1409723425],"iteration":320,"passed_time":5.25428647,"remaining_time":11.11420721},
{"learn":[0.1408026786],"iteration":321,"passed_time":5.267735981,"remaining_time":11.09169253},
{"learn":[0.140552583],"iteration":322,"passed_time":5.280886877,"remaining_time":11.0686081},
{"learn":[0.1402411811],"iteration":323,"passed_time":5.292905602,"remaining_time":11.0432228},
{"learn":[0.1398740297],"iteration":324,"passed_time":5.306143078,"remaining_time":11.02045101},
{"learn":[0.1396793707],"iteration":325,"passed_time":5.321207201,"remaining_time":11.00151428},
{"learn":[0.1394114631],"iteration":326,"passed_time":5.335399229,"remaining_time":10.98080636},
{"learn":[0.1392494326],"iteration":327,"passed_time":5.347445078,"remaining_time":10.95574114},
{"learn":[0.1390759474],"iteration":328,"passed_time":5.360785634,"remaining_time":10.93339562},
{"learn":[0.1389503343],"iteration":329,"passed_time":5.37292573,"remaining_time":10.90866739},
{"learn":[0.1387250112],"iteration":330,"passed_time":5.384596717,"remaining_time":10.88306708},
{"learn":[0.138476086],"iteration":331,"passed_time":5.398546753,"remaining_time":10.86213624},
{"learn":[0.1378134777],"iteration":332,"passed_time":5.411259454,"remaining_time":10.83876894},
{"learn":[0.1376126781],"iteration":333,"passed_time":5.423277846,"remaining_time":10.81408097},
{"learn":[0.1374583669],"iteration":334,"passed_time":5.435904634,"remaining_time":10.79067636},
{"learn":[0.1370359733],"iteration":335,"passed_time":5.447575079,"remaining_time":10.76544599},
{"learn":[0.1368772234],"iteration":336,"passed_time":5.460587688,"remaining_time":10.74293661},
{"learn":[0.1366709655],"iteration":337,"passed_time":5.473424844,"remaining_time":10.72013978},
{"learn":[0.1364420582],"iteration":338,"passed_time":5.484848547,"remaining_time":10.69464569},
{"learn":[0.1363259959],"iteration":339,"passed_time":5.497059432,"remaining_time":10.67076243},
{"learn":[0.1361704062],"iteration":340,"passed_time":5.509046408,"remaining_time":10.64651491},
{"learn":[0.1358896123],"iteration":341,"passed_time":5.521240669,"remaining_time":10.6227379},
{"learn":[0.1356206582],"iteration":342,"passed_time":5.535857725,"remaining_time":10.60366917},
{"learn":[0.1354711317],"iteration":343,"passed_time":5.548049152,"remaining_time":10.58000071},
{"learn":[0.1352364652],"iteration":344,"passed_time":5.5621476,"remaining_time":10.56001936},
{"learn":[0.1349019929],"iteration":345,"passed_time":5.577018813,"remaining_time":10.54153267},
{"learn":[0.1347708903],"iteration":346,"passed_time":5.590511989,"remaining_time":10.52047357},
{"learn":[0.134606686],"iteration":347,"passed_time":5.603171776,"remaining_time":10.49789655},
{"learn":[0.1342117574],"iteration":348,"passed_time":5.615755149,"remaining_time":10.47523382},
{"learn":[0.1340321035],"iteration":349,"passed_time":5.628206234,"remaining_time":10.45238301},
{"learn":[0.1338555298],"iteration":350,"passed_time":5.640825356,"remaining_time":10.42990215},
{"learn":[0.1337352311],"iteration":351,"passed_time":5.653486976,"remaining_time":10.40755557},
{"learn":[0.1336074355],"iteration":352,"passed_time":5.665719528,"remaining_time":10.38447743},
{"learn":[0.1334775038],"iteration":353,"passed_time":5.678063075,"remaining_time":10.36166313},
{"learn":[0.1332988069],"iteration":354,"passed_time":5.691349758,"remaining_time":10.34062139},
{"learn":[0.1331486404],"iteration":355,"passed_time":5.704998512,"remaining_time":10.32027821},
{"learn":[0.1328477294],"iteration":356,"passed_time":5.718378775,"remaining_time":10.29948894},
{"learn":[0.1326940284],"iteration":357,"passed_time":5.732229648,"remaining_time":10.27958501},
{"learn":[0.1325089295],"iteration":358,"passed_time":5.744498739,"remaining_time":10.25689051},
{"learn":[0.1322937169],"iteration":359,"passed_time":5.757635469,"remaining_time":10.23579639},
{"learn":[0.1321517978],"iteration":360,"passed_time":5.77011197,"remaining_time":10.2135777},
{"learn":[0.1319664499],"iteration":361,"passed_time":5.783563439,"remaining_time":10.19313114},
{"learn":[0.1317864822],"iteration":362,"passed_time":5.795564415,"remaining_time":10.17017777},
{"learn":[0.1316527079],"iteration":363,"passed_time":5.807425395,"remaining_time":10.14703998},
{"learn":[0.1314269894],"iteration":364,"passed_time":5.819959728,"remaining_time":10.12513542},
{"learn":[0.1312985637],"iteration":365,"passed_time":5.832083574,"remaining_time":10.102571},
{"learn":[0.1311113452],"iteration":366,"passed_time":5.845259844,"remaining_time":10.0818787},
{"learn":[0.1308642505],"iteration":367,"passed_time":5.857749595,"remaining_time":10.06004822},
{"learn":[0.1306708602],"iteration":368,"passed_time":5.869309461,"remaining_time":10.03667824},
{"learn":[0.1304985712],"iteration":369,"passed_time":5.882356401,"remaining_time":10.01590414},
{"learn":[0.1302632484],"iteration":370,"passed_time":5.895266222,"remaining_time":9.994939228},
{"learn":[0.1301070551],"iteration":371,"passed_time":5.908968557,"remaining_time":9.975355522},
{"learn":[0.1299133666],"iteration":372,"passed_time":5.921053322,"remaining_time":9.95308427},
{"learn":[0.1294124836],"iteration":373,"passed_time":5.933256457,"remaining_time":9.931065621},
{"learn":[0.1292827535],"iteration":374,"passed_time":5.946632762,"remaining_time":9.911054604},
{"learn":[0.1291805249],"iteration":375,"passed_time":5.957790683,"remaining_time":9.887397303},
{"learn":[0.1290427299],"iteration":376,"passed_time":5.969699078,"remaining_time":9.865046487},
{"learn":[0.1288587027],"iteration":377,"passed_time":5.98384469,"remaining_time":9.846432268},
{"learn":[0.1286755699],"iteration":378,"passed_time":5.996873424,"remaining_time":9.826011599},
{"learn":[0.1284664457],"iteration":379,"passed_time":6.00989224,"remaining_time":9.805613655},
{"learn":[0.1283227683],"iteration":380,"passed_time":6.022896474,"remaining_time":9.785230755},
{"learn":[0.1279458505],"iteration":381,"passed_time":6.03559726,"remaining_time":9.764395567},
{"learn":[0.127831472],"iteration":382,"passed_time":6.047951765,"remaining_time":9.743045011},
{"learn":[0.1277015495],"iteration":383,"passed_time":6.059738331,"remaining_time":9.72083024},
{"learn":[0.1275834414],"iteration":384,"passed_time":6.071166076,"remaining_time":9.698096459},
{"learn":[0.1275009815],"iteration":385,"passed_time":6.082707359,"remaining_time":9.675601861},
{"learn":[0.1273346451],"iteration":386,"passed_time":6.095715634,"remaining_time":9.655487555},
{"learn":[0.1271438734],"iteration":387,"passed_time":6.10774865,"remaining_time":9.633871582},
{"learn":[0.1269846259],"iteration":388,"passed_time":6.119866164,"remaining_time":9.612437599},
{"learn":[0.1267969449],"iteration":389,"passed_time":6.134878372,"remaining_time":9.595578993},
{"learn":[0.1266052617],"iteration":390,"passed_time":6.148696163,"remaining_time":9.576869471},
{"learn":[0.1265273521],"iteration":391,"passed_time":6.163057601,"remaining_time":9.559028116},
{"learn":[0.1264209116],"iteration":392,"passed_time":6.177098217,"remaining_time":9.540708951},
{"learn":[0.1262449542],"iteration":393,"passed_time":6.190156324,"remaining_time":9.520900337},
{"learn":[0.1260323446],"iteration":394,"passed_time":6.203100935,"remaining_time":9.500952065},
{"learn":[0.1259104968],"iteration":395,"passed_time":6.215708141,"remaining_time":9.480524538},
{"learn":[0.1255777582],"iteration":396,"passed_time":6.229968541,"remaining_time":9.462647431},
{"learn":[0.1254056526],"iteration":397,"passed_time":6.24201989,"remaining_time":9.44144717},
{"learn":[0.1250865486],"iteration":398,"passed_time":6.255152161,"remaining_time":9.421920925},
{"learn":[0.1249527585],"iteration":399,"passed_time":6.267397045,"remaining_time":9.401095568},
{"learn":[0.1248442738],"iteration":400,"passed_time":6.280825724,"remaining_time":9.382081318},
{"learn":[0.1246943617],"iteration":401,"passed_time":6.293286767,"remaining_time":9.36165544},
{"learn":[0.1245881416],"iteration":402,"passed_time":6.306057384,"remaining_time":9.341727688},
{"learn":[0.1243881018],"iteration":403,"passed_time":6.319424356,"remaining_time":9.322715139},
{"learn":[0.1242347165],"iteration":404,"passed_time":6.332333468,"remaining_time":9.303057811},
{"learn":[0.124102565],"iteration":405,"passed_time":6.345537987,"remaining_time":9.283865921},
{"learn":[0.1239038401],"iteration":406,"passed_time":6.3578992,"remaining_time":9.263474756},
{"learn":[0.1237373973],"iteration":407,"passed_time":6.370962182,"remaining_time":9.244141206},
{"learn":[0.1235807037],"iteration":408,"passed_time":6.384506981,"remaining_time":9.225534538},
{"learn":[0.1234293545],"iteration":409,"passed_time":6.396444209,"remaining_time":9.204639228},
{"learn":[0.1233016443],"iteration":410,"passed_time":6.40793091,"remaining_time":9.183141864},
{"learn":[0.1231416889],"iteration":411,"passed_time":6.421244592,"remaining_time":9.164300534},
{"learn":[0.1229740716],"iteration":412,"passed_time":6.43402525,"remaining_time":9.144728382},
{"learn":[0.1228799405],"iteration":413,"passed_time":6.44675541,"remaining_time":9.125117561},
{"learn":[0.1227400765],"iteration":414,"passed_time":6.458173321,"remaining_time":9.103690104},
{"learn":[0.1225667783],"iteration":415,"passed_time":6.472502928,"remaining_time":9.086398341},
{"learn":[0.1224383539],"iteration":416,"passed_time":6.484888432,"remaining_time":9.066402772},
{"learn":[0.1222840492],"iteration":417,"passed_time":6.497759296,"remaining_time":9.047119402},
{"learn":[0.1221468771],"iteration":418,"passed_time":6.510210631,"remaining_time":9.027284909},
{"learn":[0.1219791657],"iteration":419,"passed_time":6.523004122,"remaining_time":9.007958074},
{"learn":[0.1218730605],"iteration":420,"passed_time":6.534598111,"remaining_time":8.987012604},
{"learn":[0.1217272365],"iteration":421,"passed_time":6.547337604,"remaining_time":8.967680415},
{"learn":[0.1215472358],"iteration":422,"passed_time":6.56054454,"remaining_time":8.94901702},
{"learn":[0.121374836],"iteration":423,"passed_time":6.573179661,"remaining_time":8.929602558},
{"learn":[0.1212807963],"iteration":424,"passed_time":6.58586128,"remaining_time":8.910282909},
{"learn":[0.1211371476],"iteration":425,"passed_time":6.597895171,"remaining_time":8.890121663},
{"learn":[0.121077601],"iteration":426,"passed_time":6.610265135,"remaining_time":8.870449467},
{"learn":[0.1208876022],"iteration":427,"passed_time":6.623843933,"remaining_time":8.852426938},
{"learn":[0.1207122059],"iteration":428,"passed_time":6.635590584,"remaining_time":8.831986534},
{"learn":[0.1205723376],"iteration":429,"passed_time":6.64876852,"remaining_time":8.813483852},
{"learn":[0.120447039],"iteration":430,"passed_time":6.663860518,"remaining_time":8.797532795},
{"learn":[0.1203012286],"iteration":431,"passed_time":6.678118043,"remaining_time":8.780488538},
{"learn":[0.1200640351],"iteration":432,"passed_time":6.693229082,"remaining_time":8.764574803},
{"learn":[0.1199423894],"iteration":433,"passed_time":6.708104629,"remaining_time":8.748357649},
{"learn":[0.1198603479],"iteration":434,"passed_time":6.721695176,"remaining_time":8.730477643},
{"learn":[0.1197607683],"iteration":435,"passed_time":6.734346005,"remaining_time":8.711401713},
{"learn":[0.1196130449],"iteration":436,"passed_time":6.749050641,"remaining_time":8.695001169},
{"learn":[0.1194855678],"iteration":437,"passed_time":6.763175838,"remaining_time":8.677864888},
{"learn":[0.1193683418],"iteration":438,"passed_time":6.777644231,"remaining_time":8.661180897},
{"learn":[0.119248279],"iteration":439,"passed_time":6.790420473,"remaining_time":8.642353329},
{"learn":[0.1191275394],"iteration":440,"passed_time":6.80390744,"remaining_time":8.624454102},
{"learn":[0.1189906053],"iteration":441,"passed_time":6.818625159,"remaining_time":8.608128594},
{"learn":[0.118865486],"iteration":442,"passed_time":6.833025096,"remaining_time":8.591410787},
{"learn":[0.1187596437],"iteration":443,"passed_time":6.84724679,"remaining_time":8.574480214},
{"learn":[0.1186196288],"iteration":444,"passed_time":6.862187001,"remaining_time":8.558457945},
{"learn":[0.118374214],"iteration":445,"passed_time":6.875837338,"remaining_time":8.540838308},
{"learn":[0.1182616162],"iteration":446,"passed_time":6.888800657,"remaining_time":8.522386495},
{"learn":[0.1181550902],"iteration":447,"passed_time":6.912660029,"remaining_time":8.517384679},
{"learn":[0.1179948333],"iteration":448,"passed_time":6.927759027,"remaining_time":8.501548383},
{"learn":[0.1179229648],"iteration":449,"passed_time":6.941064417,"remaining_time":8.483523177},
{"learn":[0.1177990262],"iteration":450,"passed_time":6.957708614,"remaining_time":8.469583212},
{"learn":[0.1176006013],"iteration":451,"passed_time":6.972346293,"remaining_time":8.453198603},
{"learn":[0.1175236352],"iteration":452,"passed_time":6.985940966,"remaining_time":8.43556227},
{"learn":[0.1173824214],"iteration":453,"passed_time":7.001343078,"remaining_time":8.420117446},
{"learn":[0.1171947912],"iteration":454,"passed_time":7.025556022,"remaining_time":8.415226444},
{"learn":[0.1169788777],"iteration":455,"passed_time":7.039459435,"remaining_time":8.397951606},
{"learn":[0.1168467958],"iteration":456,"passed_time":7.052155012,"remaining_time":8.379256393},
{"learn":[0.1165995672],"iteration":457,"passed_time":7.06444952,"remaining_time":8.36011275},
{"learn":[0.1165177623],"iteration":458,"passed_time":7.078478386,"remaining_time":8.343043152},
{"learn":[0.1163973926],"iteration":459,"passed_time":7.092296468,"remaining_time":8.325739332},
{"learn":[0.116325142],"iteration":460,"passed_time":7.105101292,"remaining_time":8.307265935},
{"learn":[0.1161172979],"iteration":461,"passed_time":7.117287844,"remaining_time":8.2880971},
{"learn":[0.1159973119],"iteration":462,"passed_time":7.130035087,"remaining_time":8.269608729},
{"learn":[0.1159357458],"iteration":463,"passed_time":7.140992805,"remaining_time":8.249077896},
{"learn":[0.1158600117],"iteration":464,"passed_time":7.153999748,"remaining_time":8.230945946},
{"learn":[0.1157698925],"iteration":465,"passed_time":7.166292047,"remaining_time":8.212017067},
{"learn":[0.115577581],"iteration":466,"passed_time":7.180967267,"remaining_time":8.195836302},
{"learn":[0.1154503276],"iteration":467,"passed_time":7.197534674,"remaining_time":8.18181292},
{"learn":[0.1153740393],"iteration":468,"passed_time":7.210244042,"remaining_time":8.163410632},
{"learn":[0.1152113239],"iteration":469,"passed_time":7.223214236,"remaining_time":8.145326691},
{"learn":[0.1151428472],"iteration":470,"passed_time":7.235501577,"remaining_time":8.126497525},
{"learn":[0.1150439804],"iteration":471,"passed_time":7.247432388,"remaining_time":8.107297248},
{"learn":[0.1148308255],"iteration":472,"passed_time":7.26064424,"remaining_time":8.089554999},
{"learn":[0.1147091927],"iteration":473,"passed_time":7.32009272,"remaining_time":8.123140867},
{"learn":[0.114566552],"iteration":474,"passed_time":7.343287323,"remaining_time":8.116264936},
{"learn":[0.1144778422],"iteration":475,"passed_time":7.356289599,"remaining_time":8.098100315},
{"learn":[0.1143044369],"iteration":476,"passed_time":7.370402171,"remaining_time":8.081174707},
{"learn":[0.1142358964],"iteration":477,"passed_time":7.383610356,"remaining_time":8.063273234},
{"learn":[0.1141711487],"iteration":478,"passed_time":7.396364932,"remaining_time":8.044897974},
{"learn":[0.1140678975],"iteration":479,"passed_time":7.40979911,"remaining_time":8.027282369},
{"learn":[0.1139959419],"iteration":480,"passed_time":7.422949755,"remaining_time":8.009378218},
{"learn":[0.1139101047],"iteration":481,"passed_time":7.43519064,"remaining_time":7.990516082},
{"learn":[0.1137976301],"iteration":482,"passed_time":7.447854885,"remaining_time":7.972134525},
{"learn":[0.1137025538],"iteration":483,"passed_time":7.460119935,"remaining_time":7.953351005},
{"learn":[0.1136068003],"iteration":484,"passed_time":7.473811896,"remaining_time":7.936109539},
{"learn":[0.1134935408],"iteration":485,"passed_time":7.486844046,"remaining_time":7.918184855},
{"learn":[0.1134175551],"iteration":486,"passed_time":7.499349463,"remaining_time":7.899725409},
{"learn":[0.1133204933],"iteration":487,"passed_time":7.5112579,"remaining_time":7.880664026},
{"learn":[0.113192615],"iteration":488,"passed_time":7.524427086,"remaining_time":7.862949368},
{"learn":[0.1131151743],"iteration":489,"passed_time":7.536329482,"remaining_time":7.843934767},
{"learn":[0.1129793479],"iteration":490,"passed_time":7.548589282,"remaining_time":7.825319643},
{"learn":[0.1128408168],"iteration":491,"passed_time":7.562044126,"remaining_time":7.80796426},
{"learn":[0.1127145452],"iteration":492,"passed_time":7.574922656,"remaining_time":7.790032021},
{"learn":[0.1126041052],"iteration":493,"passed_time":7.589708081,"remaining_time":7.774073459},
{"learn":[0.1125284456],"iteration":494,"passed_time":7.603907066,"remaining_time":7.75752135},
{"learn":[0.1124210785],"iteration":495,"passed_time":7.617985139,"remaining_time":7.740855868},
{"learn":[0.1122151099],"iteration":496,"passed_time":7.633412251,"remaining_time":7.725566121},
{"learn":[0.1121290078],"iteration":497,"passed_time":7.647058964,"remaining_time":7.708481124},
{"learn":[0.1120053903],"iteration":498,"passed_time":7.659184643,"remaining_time":7.689882778},
{"learn":[0.1118979342],"iteration":499,"passed_time":7.672191002,"remaining_time":7.672191002},
{"learn":[0.1117460573],"iteration":500,"passed_time":7.684329848,"remaining_time":7.653653881},
{"learn":[0.1115084784],"iteration":501,"passed_time":7.697677196,"remaining_time":7.636341122},
{"learn":[0.1114044452],"iteration":502,"passed_time":7.709231186,"remaining_time":7.617272166},
{"learn":[0.1113124092],"iteration":503,"passed_time":7.721812726,"remaining_time":7.59924427},
{"learn":[0.1111951777],"iteration":504,"passed_time":7.733503212,"remaining_time":7.580364534},
{"learn":[0.1109736709],"iteration":505,"passed_time":7.747163715,"remaining_time":7.563436513},
{"learn":[0.110865944],"iteration":506,"passed_time":7.758987405,"remaining_time":7.544735288},
{"learn":[0.1108103912],"iteration":507,"passed_time":7.77161011,"remaining_time":7.526834989},
{"learn":[0.1107503939],"iteration":508,"passed_time":7.783769455,"remaining_time":7.508508453},
{"learn":[0.110476194],"iteration":509,"passed_time":7.797436584,"remaining_time":7.491654757},
{"learn":[0.1103442728],"iteration":510,"passed_time":7.811718734,"remaining_time":7.475402076},
{"learn":[0.110258242],"iteration":511,"passed_time":7.823855163,"remaining_time":7.457111952},
{"learn":[0.1101482648],"iteration":512,"passed_time":7.836256,"remaining_time":7.439096827},
{"learn":[0.1101122],"iteration":513,"passed_time":7.847305799,"remaining_time":7.419826106},
{"learn":[0.1100345585],"iteration":514,"passed_time":7.858753252,"remaining_time":7.4009618},
{"learn":[0.1099577819],"iteration":515,"passed_time":7.872035685,"remaining_time":7.383847425},
{"learn":[0.1099302256],"iteration":516,"passed_time":7.883656256,"remaining_time":7.365195303},
{"learn":[0.1098251845],"iteration":517,"passed_time":7.896178548,"remaining_time":7.347409382},
{"learn":[0.1097317147],"iteration":518,"passed_time":7.908472722,"remaining_time":7.32943233},
{"learn":[0.1096336483],"iteration":519,"passed_time":7.92031712,"remaining_time":7.311061956},
{"learn":[0.1095039178],"iteration":520,"passed_time":7.933502556,"remaining_time":7.293949567},
{"learn":[0.1094035679],"iteration":521,"passed_time":7.999799391,"remaining_time":7.325486799},
{"learn":[0.1092423308],"iteration":522,"passed_time":8.015743569,"remaining_time":7.31072597},
{"learn":[0.1091376313],"iteration":523,"passed_time":8.029489361,"remaining_time":7.293963618},
{"learn":[0.1090830458],"iteration":524,"passed_time":8.042915248,"remaining_time":7.276923319},
{"learn":[0.1089816446],"iteration":525,"passed_time":8.055984979,"remaining_time":7.259575818},
{"learn":[0.1089086273],"iteration":526,"passed_time":8.069297495,"remaining_time":7.242462457},
{"learn":[0.1087812766],"iteration":527,"passed_time":8.083118576,"remaining_time":7.225818121},
{"learn":[0.1086845915],"iteration":528,"passed_time":8.097808046,"remaining_time":7.209957636},
{"learn":[0.1085689061],"iteration":529,"passed_time":8.110898569,"remaining_time":7.192683636},
{"learn":[0.1084867156],"iteration":530,"passed_time":8.123563314,"remaining_time":7.17504933},
{"learn":[0.1083617483],"iteration":531,"passed_time":8.137531224,"remaining_time":7.158580099},
{"learn":[0.1083075129],"iteration":532,"passed_time":8.149221543,"remaining_time":7.140124692},
{"learn":[0.1080248963],"iteration":533,"passed_time":8.161252893,"remaining_time":7.121992225},
{"learn":[0.1079540439],"iteration":534,"passed_time":8.173166163,"remaining_time":7.103779936},
{"learn":[0.1078676022],"iteration":535,"passed_time":8.186073483,"remaining_time":7.086451672},
{"learn":[0.1077420615],"iteration":536,"passed_time":8.199429622,"remaining_time":7.069526844},
{"learn":[0.107587164],"iteration":537,"passed_time":8.212279195,"remaining_time":7.052180275},
{"learn":[0.1074813965],"iteration":538,"passed_time":8.22410026,"remaining_time":7.033970723},
{"learn":[0.1073601507],"iteration":539,"passed_time":8.235998364,"remaining_time":7.015850458},
{"learn":[0.1072195304],"iteration":540,"passed_time":8.249813029,"remaining_time":6.999379261},
{"learn":[0.1071375498],"iteration":541,"passed_time":8.261798088,"remaining_time":6.981371816},
{"learn":[0.107078727],"iteration":542,"passed_time":8.275601379,"remaining_time":6.964916814},
{"learn":[0.1069760885],"iteration":543,"passed_time":8.29023085,"remaining_time":6.949164095},
{"learn":[0.1068881308],"iteration":544,"passed_time":8.304536874,"remaining_time":6.933145464},
{"learn":[0.1068651069],"iteration":545,"passed_time":8.317513317,"remaining_time":6.916027557},
{"learn":[0.1067361972],"iteration":546,"passed_time":8.332166371,"remaining_time":6.900313284},
{"learn":[0.1065932017],"iteration":547,"passed_time":8.348713946,"remaining_time":6.886165517},
{"learn":[0.1064731746],"iteration":548,"passed_time":8.362926764,"remaining_time":6.870091021},
{"learn":[0.1063401564],"iteration":549,"passed_time":8.378128675,"remaining_time":6.854832552},
{"learn":[0.1062648628],"iteration":550,"passed_time":8.392983097,"remaining_time":6.839291127},
{"learn":[0.106116582],"iteration":551,"passed_time":8.408319754,"remaining_time":6.824143568},
{"learn":[0.1059947644],"iteration":552,"passed_time":8.423938401,"remaining_time":6.809223264},
{"learn":[0.1059488254],"iteration":553,"passed_time":8.437898603,"remaining_time":6.792965301},
{"learn":[0.1058609911],"iteration":554,"passed_time":8.452277249,"remaining_time":6.777051128},
{"learn":[0.1056574729],"iteration":555,"passed_time":8.467676612,"remaining_time":6.761957582},
{"learn":[0.1055757493],"iteration":556,"passed_time":8.482247085,"remaining_time":6.746203696},
{"learn":[0.1055030456],"iteration":557,"passed_time":8.496024918,"remaining_time":6.72982619},
{"learn":[0.1053687323],"iteration":558,"passed_time":8.509910539,"remaining_time":6.713543019},
{"learn":[0.1052278744],"iteration":559,"passed_time":8.524610675,"remaining_time":6.697908388},
{"learn":[0.1051772232],"iteration":560,"passed_time":8.53743454,"remaining_time":6.680808847},
{"learn":[0.1050532228],"iteration":561,"passed_time":8.552432291,"remaining_time":6.665418761},
{"learn":[0.1049524705],"iteration":562,"passed_time":8.572175134,"remaining_time":6.653713203},
{"learn":[0.1049052338],"iteration":563,"passed_time":8.58706418,"remaining_time":6.638226919},
{"learn":[0.1047964008],"iteration":564,"passed_time":8.600975967,"remaining_time":6.621990346},
{"learn":[0.1046805569],"iteration":565,"passed_time":8.615948552,"remaining_time":6.606575392},
{"learn":[0.1046498576],"iteration":566,"passed_time":8.630500276,"remaining_time":6.590840599},
{"learn":[0.1045789486],"iteration":567,"passed_time":8.643728378,"remaining_time":6.574103273},
{"learn":[0.1045109597],"iteration":568,"passed_time":8.657300093,"remaining_time":6.557638559},
{"learn":[0.1044892581],"iteration":569,"passed_time":8.672092767,"remaining_time":6.54210507},
{"learn":[0.1043870359],"iteration":570,"passed_time":8.689393066,"remaining_time":6.528458188},
{"learn":[0.1041563458],"iteration":571,"passed_time":8.705501489,"remaining_time":6.513906708},
{"learn":[0.1040549736],"iteration":572,"passed_time":8.71918945,"remaining_time":6.497546065},
{"learn":[0.1040005512],"iteration":573,"passed_time":8.733673093,"remaining_time":6.481785257},
{"learn":[0.1038459586],"iteration":574,"passed_time":8.749203992,"remaining_time":6.466802951},
{"learn":[0.1037764532],"iteration":575,"passed_time":8.764004125,"remaining_time":6.451280814},
{"learn":[0.1036631496],"iteration":576,"passed_time":8.779357614,"remaining_time":6.436166847},
{"learn":[0.1035690873],"iteration":577,"passed_time":8.794488652,"remaining_time":6.420889639},
{"learn":[0.103470286],"iteration":578,"passed_time":8.809684021,"remaining_time":6.405659712},
{"learn":[0.1034043217],"iteration":579,"passed_time":8.824474237,"remaining_time":6.390136517},
{"learn":[0.1032603053],"iteration":580,"passed_time":8.83875872,"remaining_time":6.374251125},
{"learn":[0.1031538479],"iteration":581,"passed_time":8.859609193,"remaining_time":6.363087015},
{"learn":[0.1031048821],"iteration":582,"passed_time":8.894453742,"remaining_time":6.36189916},
{"learn":[0.1030051462],"iteration":583,"passed_time":8.910204009,"remaining_time":6.346994637},
{"learn":[0.1028946183],"iteration":584,"passed_time":8.927334689,"remaining_time":6.333066489},
{"learn":[0.1027782897],"iteration":585,"passed_time":8.941245101,"remaining_time":6.316852341},
{"learn":[0.1026681561],"iteration":586,"passed_time":8.957323025,"remaining_time":6.302171055},
{"learn":[0.1025785386],"iteration":587,"passed_time":8.969572575,"remaining_time":6.284802553},
{"learn":[0.1024462508],"iteration":588,"passed_time":8.983881307,"remaining_time":6.268888315},
{"learn":[0.1023312971],"iteration":589,"passed_time":8.997439064,"remaining_time":6.252457655},
{"learn":[0.1022430865],"iteration":590,"passed_time":9.010400175,"remaining_time":6.23562381},
{"learn":[0.1021477044],"iteration":591,"passed_time":9.023813978,"remaining_time":6.219115039},
{"learn":[0.1020709206],"iteration":592,"passed_time":9.039470666,"remaining_time":6.204156089},
{"learn":[0.1020135503],"iteration":593,"passed_time":9.051923293,"remaining_time":6.18700481},
{"learn":[0.1019068371],"iteration":594,"passed_time":9.065567089,"remaining_time":6.170680119},
{"learn":[0.1018018641],"iteration":595,"passed_time":9.080237392,"remaining_time":6.155060246},
{"learn":[0.1016767009],"iteration":596,"passed_time":9.094956986,"remaining_time":6.139476826},
{"learn":[0.1015299096],"iteration":597,"passed_time":9.110223311,"remaining_time":6.124263831},
{"learn":[0.1014438766],"iteration":598,"passed_time":9.122815975,"remaining_time":6.107260778},
{"learn":[0.1013843778],"iteration":599,"passed_time":9.134622791,"remaining_time":6.089748527},
{"learn":[0.1013109611],"iteration":600,"passed_time":9.147184873,"remaining_time":6.072756679},
{"learn":[0.101230262],"iteration":601,"passed_time":9.159784787,"remaining_time":6.05580456},
{"learn":[0.1011459123],"iteration":602,"passed_time":9.172309578,"remaining_time":6.038817417},
{"learn":[0.1010570256],"iteration":603,"passed_time":9.185564929,"remaining_time":6.022324026},
{"learn":[0.1009517014],"iteration":604,"passed_time":9.198621369,"remaining_time":6.005711472},
{"learn":[0.1008569136],"iteration":605,"passed_time":9.210492307,"remaining_time":5.988339883},
{"learn":[0.100848723],"iteration":606,"passed_time":9.221693018,"remaining_time":5.970552481},
{"learn":[0.1007470986],"iteration":607,"passed_time":9.233788407,"remaining_time":5.953363578},
{"learn":[0.1006849981],"iteration":608,"passed_time":9.245709594,"remaining_time":5.936079558},
{"learn":[0.1005438116],"iteration":609,"passed_time":9.25803635,"remaining_time":5.919072421},
{"learn":[0.1004828762],"iteration":610,"passed_time":9.272133006,"remaining_time":5.903207429},
{"learn":[0.1004259784],"iteration":611,"passed_time":9.284326558,"remaining_time":5.886141674},
{"learn":[0.1003229373],"iteration":612,"passed_time":9.296702313,"remaining_time":5.869206844},
{"learn":[0.1001375864],"iteration":613,"passed_time":9.310421148,"remaining_time":5.853131211},
{"learn":[0.1000270865],"iteration":614,"passed_time":9.322675074,"remaining_time":5.836146184},
{"learn":[0.09992394236],"iteration":615,"passed_time":9.336245956,"remaining_time":5.819997479},
{"learn":[0.09981900121],"iteration":616,"passed_time":9.347760697,"remaining_time":5.802580789},
{"learn":[0.09969243991],"iteration":617,"passed_time":9.36011437,"remaining_time":5.785701762},
{"learn":[0.09965336213],"iteration":618,"passed_time":9.371839813,"remaining_time":5.768450676},
{"learn":[0.09954010813],"iteration":619,"passed_time":9.385239742,"remaining_time":5.752243713},
{"learn":[0.09938790877],"iteration":620,"passed_time":9.397535791,"remaining_time":5.735372085},
{"learn":[0.09930621812],"iteration":621,"passed_time":9.410331532,"remaining_time":5.718818841},
{"learn":[0.0992095032],"iteration":622,"passed_time":9.422605248,"remaining_time":5.701961763},
{"learn":[0.09912419439],"iteration":623,"passed_time":9.435403406,"remaining_time":5.685435385},
{"learn":[0.09891658354],"iteration":624,"passed_time":9.448913373,"remaining_time":5.669348024},
{"learn":[0.09882426358],"iteration":625,"passed_time":9.462057269,"remaining_time":5.653050189},
{"learn":[0.09865260237],"iteration":626,"passed_time":9.474979589,"remaining_time":5.636630601},
{"learn":[0.0985094081],"iteration":627,"passed_time":9.489297487,"remaining_time":5.62104883},
{"learn":[0.09844954321],"iteration":628,"passed_time":9.503231148,"remaining_time":5.605244445},
{"learn":[0.0984021623],"iteration":629,"passed_time":9.515433951,"remaining_time":5.588429463},
{"learn":[0.09831877458],"iteration":630,"passed_time":9.52881013,"remaining_time":5.572315274},
{"learn":[0.09822052493],"iteration":631,"passed_time":9.542674919,"remaining_time":5.556494257},
{"learn":[0.09813417884],"iteration":632,"passed_time":9.555244292,"remaining_time":5.539928365},
{"learn":[0.09805293889],"iteration":633,"passed_time":9.567034067,"remaining_time":5.522925029},
{"learn":[0.09799714235],"iteration":634,"passed_time":9.579373781,"remaining_time":5.506254221},
{"learn":[0.09783203013],"iteration":635,"passed_time":9.593510269,"remaining_time":5.490625374},
{"learn":[0.09775676991],"iteration":636,"passed_time":9.606187722,"remaining_time":5.474169769},
{"learn":[0.09767318753],"iteration":637,"passed_time":9.619221996,"remaining_time":5.457928468},
{"learn":[0.09763711134],"iteration":638,"passed_time":9.633169782,"remaining_time":5.442213289},
{"learn":[0.09754282518],"iteration":639,"passed_time":9.648114327,"remaining_time":5.427064309},
{"learn":[0.09741915483],"iteration":640,"passed_time":9.662084695,"remaining_time":5.411370367},
{"learn":[0.09732045514],"iteration":641,"passed_time":9.676860037,"remaining_time":5.396130675},
{"learn":[0.09722158675],"iteration":642,"passed_time":9.690640911,"remaining_time":5.380340288},
{"learn":[0.0971362511],"iteration":643,"passed_time":9.703829222,"remaining_time":5.364228576},
{"learn":[0.0970352525],"iteration":644,"passed_time":9.716861122,"remaining_time":5.348039842},
{"learn":[0.09692997189],"iteration":645,"passed_time":9.730503085,"remaining_time":5.332195189},
{"learn":[0.09685086153],"iteration":646,"passed_time":9.742458437,"remaining_time":5.315437138},
{"learn":[0.09680836163],"iteration":647,"passed_time":9.753896931,"remaining_time":5.298413148},
{"learn":[0.0967195342],"iteration":648,"passed_time":9.766536427,"remaining_time":5.282055911},
{"learn":[0.09669000735],"iteration":649,"passed_time":9.77866569,"remaining_time":5.265435372},
{"learn":[0.09661045115],"iteration":650,"passed_time":9.791908208,"remaining_time":5.249425445},
{"learn":[0.09657427989],"iteration":651,"passed_time":9.803380743,"remaining_time":5.232479292},
{"learn":[0.09652318717],"iteration":652,"passed_time":9.816565887,"remaining_time":5.216459974},
{"learn":[0.09641377716],"iteration":653,"passed_time":9.828273998,"remaining_time":5.199667895},
{"learn":[0.09624494029],"iteration":654,"passed_time":9.839953401,"remaining_time":5.182876219},
{"learn":[0.09617623613],"iteration":655,"passed_time":9.852768891,"remaining_time":5.166695882},
{"learn":[0.09612092595],"iteration":656,"passed_time":9.864098639,"remaining_time":5.149750126},
{"learn":[0.09603713305],"iteration":657,"passed_time":9.877922804,"remaining_time":5.134117931},
{"learn":[0.09594168049],"iteration":658,"passed_time":9.892359198,"remaining_time":5.118808022},
{"learn":[0.09593659989],"iteration":659,"passed_time":9.905351141,"remaining_time":5.102756648},
{"learn":[0.09583726745],"iteration":660,"passed_time":9.918718613,"remaining_time":5.086907125},
{"learn":[0.09575230968],"iteration":661,"passed_time":9.932733771,"remaining_time":5.071395792},
{"learn":[0.09565717377],"iteration":662,"passed_time":9.944856534,"remaining_time":5.054927077},
{"learn":[0.09559032894],"iteration":663,"passed_time":9.956831344,"remaining_time":5.038396584},
{"learn":[0.09552981295],"iteration":664,"passed_time":9.969736915,"remaining_time":5.022348671},
{"learn":[0.09547227308],"iteration":665,"passed_time":9.981255865,"remaining_time":5.005614803},
{"learn":[0.09538867157],"iteration":666,"passed_time":9.994935743,"remaining_time":4.989975416},
{"learn":[0.09529818185],"iteration":667,"passed_time":10.00764074,"remaining_time":4.973857372},
{"learn":[0.0951527714],"iteration":668,"passed_time":10.02047627,"remaining_time":4.957814117},
{"learn":[0.09509601183],"iteration":669,"passed_time":10.03338213,"remaining_time":4.941815079},
{"learn":[0.09503304896],"iteration":670,"passed_time":10.04452247,"remaining_time":4.9249596},
{"learn":[0.09494937811],"iteration":671,"passed_time":10.05633112,"remaining_time":4.90844733},
{"learn":[0.09485008872],"iteration":672,"passed_time":10.07137337,"remaining_time":4.893520194},
{"learn":[0.09480420332],"iteration":673,"passed_time":10.08576422,"remaining_time":4.878277649},
{"learn":[0.09471717495],"iteration":674,"passed_time":10.09947385,"remaining_time":4.86270963},
{"learn":[0.09464525302],"iteration":675,"passed_time":10.11282065,"remaining_time":4.846973212},
{"learn":[0.09454051266],"iteration":676,"passed_time":10.12626233,"remaining_time":4.831289118},
{"learn":[0.0944623691],"iteration":677,"passed_time":10.14019841,"remaining_time":4.815846442},
{"learn":[0.09436385208],"iteration":678,"passed_time":10.15437923,"remaining_time":4.800523906},
{"learn":[0.09426429433],"iteration":679,"passed_time":10.16750342,"remaining_time":4.78470749},
{"learn":[0.09417836489],"iteration":680,"passed_time":10.17994996,"remaining_time":4.768581553},
{"learn":[0.09412445306],"iteration":681,"passed_time":10.19273862,"remaining_time":4.752625925},
{"learn":[0.09403634145],"iteration":682,"passed_time":10.20520812,"remaining_time":4.736531441},
{"learn":[0.09398939988],"iteration":683,"passed_time":10.21780266,"remaining_time":4.720505322},
{"learn":[0.09390276474],"iteration":684,"passed_time":10.23018487,"remaining_time":4.704391583},
{"learn":[0.09381987249],"iteration":685,"passed_time":10.24301136,"remaining_time":4.688492081},
{"learn":[0.09379348548],"iteration":686,"passed_time":10.25499592,"remaining_time":4.672217938},
{"learn":[0.09374039594],"iteration":687,"passed_time":10.26731764,"remaining_time":4.656109161},
{"learn":[0.09367705966],"iteration":688,"passed_time":10.27926549,"remaining_time":4.639842623},
{"learn":[0.09357948881],"iteration":689,"passed_time":10.29161729,"remaining_time":4.623770085},
{"learn":[0.09346872325],"iteration":690,"passed_time":10.30437569,"remaining_time":4.607890144},
{"learn":[0.09339589367],"iteration":691,"passed_time":10.31615897,"remaining_time":4.591585206},
{"learn":[0.09332474118],"iteration":692,"passed_time":10.32901721,"remaining_time":4.575769528},
{"learn":[0.09331244774],"iteration":693,"passed_time":10.34035358,"remaining_time":4.559291348},
{"learn":[0.09323083031],"iteration":694,"passed_time":10.35220277,"remaining_time":4.543053014},
{"learn":[0.09316125889],"iteration":695,"passed_time":10.36450907,"remaining_time":4.527026949},
{"learn":[0.09311638418],"iteration":696,"passed_time":10.37658121,"remaining_time":4.510909765},
{"learn":[0.0929787671],"iteration":697,"passed_time":10.38915037,"remaining_time":4.495019216},
{"learn":[0.09288631788],"iteration":698,"passed_time":10.40218311,"remaining_time":4.47933779},
{"learn":[0.09278188335],"iteration":699,"passed_time":10.41532296,"remaining_time":4.46370984},
{"learn":[0.09269635039],"iteration":700,"passed_time":10.4286801,"remaining_time":4.448181669},
{"learn":[0.09262260014],"iteration":701,"passed_time":10.44067982,"remaining_time":4.432083458},
{"learn":[0.09256090009],"iteration":702,"passed_time":10.45528709,"remaining_time":4.417098528},
{"learn":[0.09249055977],"iteration":703,"passed_time":10.46825649,"remaining_time":4.401426024},
{"learn":[0.09245146042],"iteration":704,"passed_time":10.48136951,"remaining_time":4.385821285},
{"learn":[0.09238004094],"iteration":705,"passed_time":10.49255168,"remaining_time":4.369419539},
{"learn":[0.09233808508],"iteration":706,"passed_time":10.50642801,"remaining_time":4.354149091},
{"learn":[0.0922384401],"iteration":707,"passed_time":10.51985606,"remaining_time":4.338697699},
{"learn":[0.09221071099],"iteration":708,"passed_time":10.53211982,"remaining_time":4.322774145},
{"learn":[0.09208877619],"iteration":709,"passed_time":10.54553204,"remaining_time":4.30732999},
{"learn":[0.09197320705],"iteration":710,"passed_time":10.5589341,"remaining_time":4.291887418},
{"learn":[0.09181307067],"iteration":711,"passed_time":10.57212437,"remaining_time":4.276364913},
{"learn":[0.09173363459],"iteration":712,"passed_time":10.58499473,"remaining_time":4.260720179},
{"learn":[0.09164772298],"iteration":713,"passed_time":10.59863815,"remaining_time":4.245392873},
{"learn":[0.09159538747],"iteration":714,"passed_time":10.61112857,"remaining_time":4.229610688},
{"learn":[0.09146830307],"iteration":715,"passed_time":10.62441354,"remaining_time":4.214152858},
{"learn":[0.09143403826],"iteration":716,"passed_time":10.63555488,"remaining_time":4.197854995},
{"learn":[0.09137411978],"iteration":717,"passed_time":10.68844995,"remaining_time":4.197970595},
{"learn":[0.09124309108],"iteration":718,"passed_time":10.70657343,"remaining_time":4.184349284},
{"learn":[0.0911595869],"iteration":719,"passed_time":10.72289297,"remaining_time":4.170013935},
{"learn":[0.09109651633],"iteration":720,"passed_time":10.74735887,"remaining_time":4.158825415},
{"learn":[0.0910630097],"iteration":721,"passed_time":10.76204655,"remaining_time":4.143835097},
{"learn":[0.09101308252],"iteration":722,"passed_time":10.77619528,"remaining_time":4.128639134},
{"learn":[0.09098133934],"iteration":723,"passed_time":10.79182135,"remaining_time":4.114009243},
{"learn":[0.09091557014],"iteration":724,"passed_time":10.80879712,"remaining_time":4.099888561},
{"learn":[0.09075563893],"iteration":725,"passed_time":10.82284519,"remaining_time":4.084655072},
{"learn":[0.09069354695],"iteration":726,"passed_time":10.83491779,"remaining_time":4.068683021},
{"learn":[0.09063677773],"iteration":727,"passed_time":10.8474665,"remaining_time":4.05289957},
{"learn":[0.09053309934],"iteration":728,"passed_time":10.86006716,"remaining_time":4.037144308},
{"learn":[0.09046479752],"iteration":729,"passed_time":10.87285698,"remaining_time":4.021467652},
{"learn":[0.09037078214],"iteration":730,"passed_time":10.88575326,"remaining_time":4.005838068},
{"learn":[0.09032931063],"iteration":731,"passed_time":10.8976102,"remaining_time":3.989835429},
{"learn":[0.09023981642],"iteration":732,"passed_time":10.91250408,"remaining_time":3.974950327},
{"learn":[0.09006981409],"iteration":733,"passed_time":10.92534853,"remaining_time":3.959322491},
{"learn":[0.09003054499],"iteration":734,"passed_time":10.93813727,"remaining_time":3.943682145},
{"learn":[0.0900154866],"iteration":735,"passed_time":10.94888491,"remaining_time":3.927317414},
{"learn":[0.08993377529],"iteration":736,"passed_time":10.96154849,"remaining_time":3.911651632},
{"learn":[0.08987319719],"iteration":737,"passed_time":10.97293744,"remaining_time":3.895541478},
{"learn":[0.08979721535],"iteration":738,"passed_time":10.98633987,"remaining_time":3.880155219},
{"learn":[0.08968009403],"iteration":739,"passed_time":10.99922432,"remaining_time":3.864592329},
{"learn":[0.08959714771],"iteration":740,"passed_time":11.0121726,"remaining_time":3.849058978},
{"learn":[0.08950597618],"iteration":741,"passed_time":11.02496817,"remaining_time":3.833479499},
{"learn":[0.08934323104],"iteration":742,"passed_time":11.03765637,"remaining_time":3.817870374},
{"learn":[0.08927641088],"iteration":743,"passed_time":11.04912916,"remaining_time":3.801850893},
{"learn":[0.08921137487],"iteration":744,"passed_time":11.06232534,"remaining_time":3.786433507},
{"learn":[0.08915992553],"iteration":745,"passed_time":11.07512259,"remaining_time":3.770886242},
{"learn":[0.08907874985],"iteration":746,"passed_time":11.0884036,"remaining_time":3.755510189},
{"learn":[0.08902509175],"iteration":747,"passed_time":11.09995738,"remaining_time":3.739557835},
{"learn":[0.08892896859],"iteration":748,"passed_time":11.11196157,"remaining_time":3.723768162},
{"learn":[0.08885852785],"iteration":749,"passed_time":11.12351514,"remaining_time":3.707838381},
{"learn":[0.08877717864],"iteration":750,"passed_time":11.13996405,"remaining_time":3.693543341},
{"learn":[0.08870870832],"iteration":751,"passed_time":11.15523659,"remaining_time":3.678854619},
{"learn":[0.08861630444],"iteration":752,"passed_time":11.17275988,"remaining_time":3.664902643},
{"learn":[0.08855496351],"iteration":753,"passed_time":11.18590711,"remaining_time":3.649513459},
{"learn":[0.08850290023],"iteration":754,"passed_time":11.19812537,"remaining_time":3.633828762},
{"learn":[0.08843450388],"iteration":755,"passed_time":11.21156588,"remaining_time":3.618547717},
{"learn":[0.08838908919],"iteration":756,"passed_time":11.22418662,"remaining_time":3.603008388},
{"learn":[0.08830078554],"iteration":757,"passed_time":11.23616314,"remaining_time":3.587271083},
{"learn":[0.08824928883],"iteration":758,"passed_time":11.24997085,"remaining_time":3.572125132},
{"learn":[0.08817938068],"iteration":759,"passed_time":11.26232206,"remaining_time":3.556522757},
{"learn":[0.0881423482],"iteration":760,"passed_time":11.2774079,"remaining_time":3.541787762},
{"learn":[0.08805371543],"iteration":761,"passed_time":11.29281413,"remaining_time":3.527151921},
{"learn":[0.08797491353],"iteration":762,"passed_time":11.30606861,"remaining_time":3.511845688},
{"learn":[0.08795769047],"iteration":763,"passed_time":11.31829824,"remaining_time":3.496228253},
{"learn":[0.08786907566],"iteration":764,"passed_time":11.3309849,"remaining_time":3.480760069},
{"learn":[0.08776251245],"iteration":765,"passed_time":11.34689154,"remaining_time":3.466282795},
{"learn":[0.08770809761],"iteration":766,"passed_time":11.35993619,"remaining_time":3.450932376},
{"learn":[0.08764862818],"iteration":767,"passed_time":11.37315888,"remaining_time":3.435641744},
{"learn":[0.08755667439],"iteration":768,"passed_time":11.3872467,"remaining_time":3.420616368},
{"learn":[0.08743940233],"iteration":769,"passed_time":11.40030131,"remaining_time":3.405284805},
{"learn":[0.0873795022],"iteration":770,"passed_time":11.41300867,"remaining_time":3.389856013},
{"learn":[0.08731334004],"iteration":771,"passed_time":11.42628019,"remaining_time":3.374600885},
{"learn":[0.0872054132],"iteration":772,"passed_time":11.44080921,"remaining_time":3.359720168},
{"learn":[0.0871512743],"iteration":773,"passed_time":11.45291893,"remaining_time":3.344133951},
{"learn":[0.0870846059],"iteration":774,"passed_time":11.46649256,"remaining_time":3.328981711},
{"learn":[0.08701373889],"iteration":775,"passed_time":11.47863232,"remaining_time":3.31341964},
{"learn":[0.086975558],"iteration":776,"passed_time":11.49241645,"remaining_time":3.298338311},
{"learn":[0.08693396398],"iteration":777,"passed_time":11.50500145,"remaining_time":3.28291815},
{"learn":[0.08687799776],"iteration":778,"passed_time":11.51701196,"remaining_time":3.26734229},
{"learn":[0.08676954607],"iteration":779,"passed_time":11.53081138,"remaining_time":3.252280132},
{"learn":[0.08671534945],"iteration":780,"passed_time":11.54268411,"remaining_time":3.236680947},
{"learn":[0.086661236],"iteration":781,"passed_time":11.55518044,"remaining_time":3.221265136},
{"learn":[0.08665179806],"iteration":782,"passed_time":11.56699717,"remaining_time":3.205668438},
{"learn":[0.08663630803],"iteration":783,"passed_time":11.57856387,"remaining_time":3.190012496},
{"learn":[0.08656198019],"iteration":784,"passed_time":11.59139999,"remaining_time":3.174714646},
{"learn":[0.08645975561],"iteration":785,"passed_time":11.60474558,"remaining_time":3.159561775},
{"learn":[0.08639060814],"iteration":786,"passed_time":11.61727479,"remaining_time":3.144192542},
{"learn":[0.08636210088],"iteration":787,"passed_time":11.62806964,"remaining_time":3.128363914},
{"learn":[0.08630962625],"iteration":788,"passed_time":11.64172248,"remaining_time":3.113312349},
{"learn":[0.08622398893],"iteration":789,"passed_time":11.6542194,"remaining_time":3.097957055},
{"learn":[0.08616917227],"iteration":790,"passed_time":11.66614404,"remaining_time":3.082457781},
{"learn":[0.08615931571],"iteration":791,"passed_time":11.6774655,"remaining_time":3.066809121},
{"learn":[0.08610975279],"iteration":792,"passed_time":11.68965443,"remaining_time":3.051397814},
{"learn":[0.08601454758],"iteration":793,"passed_time":11.70225688,"remaining_time":3.036101911},
{"learn":[0.08596009229],"iteration":794,"passed_time":11.71476009,"remaining_time":3.020787193},
{"learn":[0.08591388929],"iteration":795,"passed_time":11.72702272,"remaining_time":3.005417884},
{"learn":[0.08586650514],"iteration":796,"passed_time":11.74014045,"remaining_time":2.990274168},
{"learn":[0.08578176336],"iteration":797,"passed_time":11.75209318,"remaining_time":2.97484063},
{"learn":[0.08573477791],"iteration":798,"passed_time":11.76515704,"remaining_time":2.959695325},
{"learn":[0.0856837236],"iteration":799,"passed_time":11.77636504,"remaining_time":2.94409126},
{"learn":[0.08562570184],"iteration":800,"passed_time":11.79030733,"remaining_time":2.929177475},
{"learn":[0.08554978791],"iteration":801,"passed_time":11.80417528,"remaining_time":2.914247763},
{"learn":[0.08548635294],"iteration":802,"passed_time":11.81600676,"remaining_time":2.898821086},
{"learn":[0.08542458555],"iteration":803,"passed_time":11.82807403,"remaining_time":2.883460833},
{"learn":[0.08534926846],"iteration":804,"passed_time":11.8412448,"remaining_time":2.868376069},
{"learn":[0.08527209486],"iteration":805,"passed_time":11.85341302,"remaining_time":2.853054746},
{"learn":[0.08520400407],"iteration":806,"passed_time":11.86770617,"remaining_time":2.83824943},
{"learn":[0.08517948041],"iteration":807,"passed_time":11.8801335,"remaining_time":2.823002021},
{"learn":[0.08513510424],"iteration":808,"passed_time":11.89312915,"remaining_time":2.807895758},
{"learn":[0.08506864577],"iteration":809,"passed_time":11.90741543,"remaining_time":2.793097446},
{"learn":[0.08504873366],"iteration":810,"passed_time":11.91999855,"remaining_time":2.777903485},
{"learn":[0.0849758606],"iteration":811,"passed_time":11.93168091,"remaining_time":2.762507403},
{"learn":[0.08495669951],"iteration":812,"passed_time":11.94385955,"remaining_time":2.747234607},
{"learn":[0.08490939397],"iteration":813,"passed_time":11.95648288,"remaining_time":2.732071026},
{"learn":[0.08483528355],"iteration":814,"passed_time":11.9689918,"remaining_time":2.716887708},
{"learn":[0.08477227216],"iteration":815,"passed_time":11.98262018,"remaining_time":2.701963373},
{"learn":[0.08474887831],"iteration":816,"passed_time":11.99516047,"remaining_time":2.686798489},
{"learn":[0.08470312572],"iteration":817,"passed_time":12.0062823,"remaining_time":2.671324425},
{"learn":[0.08466033895],"iteration":818,"passed_time":12.01913646,"remaining_time":2.656243833},
{"learn":[0.08462679138],"iteration":819,"passed_time":12.03081607,"remaining_time":2.640910845},
{"learn":[0.08457704546],"iteration":820,"passed_time":12.04184416,"remaining_time":2.625444708},
{"learn":[0.08442084574],"iteration":821,"passed_time":12.05803421,"remaining_time":2.611107164},
{"learn":[0.08430720716],"iteration":822,"passed_time":12.07120798,"remaining_time":2.596116418},
{"learn":[0.08421659196],"iteration":823,"passed_time":12.08396126,"remaining_time":2.581040269},
{"learn":[0.08420213127],"iteration":824,"passed_time":12.09525664,"remaining_time":2.565660498},
{"learn":[0.08414755737],"iteration":825,"passed_time":12.10865556,"remaining_time":2.550733739},
{"learn":[0.0841261524],"iteration":826,"passed_time":12.12113169,"remaining_time":2.535617633},
{"learn":[0.08409970446],"iteration":827,"passed_time":12.13282589,"remaining_time":2.520345474},
{"learn":[0.08407552117],"iteration":828,"passed_time":12.14380764,"remaining_time":2.504934991},
{"learn":[0.08401656236],"iteration":829,"passed_time":12.15681213,"remaining_time":2.489949472},
{"learn":[0.08395333075],"iteration":830,"passed_time":12.16943763,"remaining_time":2.474891647},
{"learn":[0.08394744781],"iteration":831,"passed_time":12.18217774,"remaining_time":2.459862813},
{"learn":[0.08387985897],"iteration":832,"passed_time":12.19568796,"remaining_time":2.444993865},
{"learn":[0.08380139874],"iteration":833,"passed_time":12.21026102,"remaining_time":2.430339723},
{"learn":[0.08376832317],"iteration":834,"passed_time":12.22347045,"remaining_time":2.415416317},
{"learn":[0.08369351665],"iteration":835,"passed_time":12.23768473,"remaining_time":2.400694133},
{"learn":[0.08361404017],"iteration":836,"passed_time":12.25463016,"remaining_time":2.386505038},
{"learn":[0.08354253395],"iteration":837,"passed_time":12.26810663,"remaining_time":2.371638752},
{"learn":[0.0834903749],"iteration":838,"passed_time":12.28072563,"remaining_time":2.356611235},
{"learn":[0.08342231367],"iteration":839,"passed_time":12.29262961,"remaining_time":2.341453259},
{"learn":[0.08335991336],"iteration":840,"passed_time":12.30574751,"remaining_time":2.326532525},
{"learn":[0.08324142433],"iteration":841,"passed_time":12.31824588,"remaining_time":2.311499821},
{"learn":[0.08321689943],"iteration":842,"passed_time":12.33070172,"remaining_time":2.296465207},
{"learn":[0.08317657704],"iteration":843,"passed_time":12.34433214,"remaining_time":2.281653807},
{"learn":[0.08308268102],"iteration":844,"passed_time":12.35667319,"remaining_time":2.266608691},
{"learn":[0.08306476232],"iteration":845,"passed_time":12.36731529,"remaining_time":2.251260703},
{"learn":[0.08300228526],"iteration":846,"passed_time":12.37930697,"remaining_time":2.236167612},
{"learn":[0.08290924833],"iteration":847,"passed_time":12.39321151,"remaining_time":2.221424705},
{"learn":[0.08283865914],"iteration":848,"passed_time":12.40678064,"remaining_time":2.206624119},
{"learn":[0.08276323748],"iteration":849,"passed_time":12.41954984,"remaining_time":2.191685266},
{"learn":[0.08271060188],"iteration":850,"passed_time":12.4311655,"remaining_time":2.176549541},
{"learn":[0.0826678595],"iteration":851,"passed_time":12.44447693,"remaining_time":2.16171665},
{"learn":[0.08258444361],"iteration":852,"passed_time":12.45746696,"remaining_time":2.146831937},
{"learn":[0.0824810377],"iteration":853,"passed_time":12.47013974,"remaining_time":2.131897427},
{"learn":[0.08232964024],"iteration":854,"passed_time":12.48307035,"remaining_time":2.117011931},
{"learn":[0.08231872961],"iteration":855,"passed_time":12.49525791,"remaining_time":2.102006003},
{"learn":[0.0822608804],"iteration":856,"passed_time":12.5086215,"remaining_time":2.087202888},
{"learn":[0.08216397355],"iteration":857,"passed_time":12.52167319,"remaining_time":2.072351508},
{"learn":[0.0820627194],"iteration":858,"passed_time":12.53347659,"remaining_time":2.057299418},
{"learn":[0.08200990791],"iteration":859,"passed_time":12.54681498,"remaining_time":2.042504765},
{"learn":[0.08197483371],"iteration":860,"passed_time":12.55841872,"remaining_time":2.027433452},
{"learn":[0.08194553521],"iteration":861,"passed_time":12.57038403,"remaining_time":2.01242807},
{"learn":[0.08188015747],"iteration":862,"passed_time":12.582722,"remaining_time":1.997488892},
{"learn":[0.08184798583],"iteration":863,"passed_time":12.59576627,"remaining_time":1.982666913},
{"learn":[0.0817752494],"iteration":864,"passed_time":12.60837448,"remaining_time":1.967780988},
{"learn":[0.0817369133],"iteration":865,"passed_time":12.6192802,"remaining_time":1.952636889},
{"learn":[0.08159490955],"iteration":866,"passed_time":12.63299066,"remaining_time":1.937932823},
{"learn":[0.08158166495],"iteration":867,"passed_time":12.64403216,"remaining_time":1.922825168},
{"learn":[0.0815640989],"iteration":868,"passed_time":12.65747251,"remaining_time":1.908088491},
{"learn":[0.08146596688],"iteration":869,"passed_time":12.66901117,"remaining_time":1.893070634},
{"learn":[0.0814173954],"iteration":870,"passed_time":12.68074661,"remaining_time":1.878089911},
{"learn":[0.08137296477],"iteration":871,"passed_time":12.69309495,"remaining_time":1.863206598},
{"learn":[0.08128530847],"iteration":872,"passed_time":12.70624522,"remaining_time":1.848445753},
{"learn":[0.08123588463],"iteration":873,"passed_time":12.72414366,"remaining_time":1.834373114},
{"learn":[0.08119333928],"iteration":874,"passed_time":12.73953765,"remaining_time":1.81993395},
{"learn":[0.08116493827],"iteration":875,"passed_time":12.75420683,"remaining_time":1.805390008},
{"learn":[0.08112880627],"iteration":876,"passed_time":12.76675437,"remaining_time":1.790548219},
{"learn":[0.08108927032],"iteration":877,"passed_time":12.78135347,"remaining_time":1.775996723},
{"learn":[0.08103383043],"iteration":878,"passed_time":12.79414,"remaining_time":1.761195609},
{"learn":[0.08101098485],"iteration":879,"passed_time":12.80672104,"remaining_time":1.746371051},
{"learn":[0.08093059717],"iteration":880,"passed_time":12.81933129,"remaining_time":1.731555532},
{"learn":[0.08087195001],"iteration":881,"passed_time":12.83149851,"remaining_time":1.716685741},
{"learn":[0.08083154094],"iteration":882,"passed_time":12.84367806,"remaining_time":1.701823707},
{"learn":[0.08072130756],"iteration":883,"passed_time":12.85700187,"remaining_time":1.687117892},
{"learn":[0.08066905444],"iteration":884,"passed_time":12.86865906,"remaining_time":1.672198635},
{"learn":[0.08058216785],"iteration":885,"passed_time":12.88244331,"remaining_time":1.657560426},
{"learn":[0.08050881268],"iteration":886,"passed_time":12.89496919,"remaining_time":1.642763831},
{"learn":[0.08044988208],"iteration":887,"passed_time":12.90610736,"remaining_time":1.627797325},
{"learn":[0.08041087253],"iteration":888,"passed_time":12.91812038,"remaining_time":1.612948663},
{"learn":[0.08034391121],"iteration":889,"passed_time":12.92994607,"remaining_time":1.598083222},
{"learn":[0.08031611615],"iteration":890,"passed_time":12.94121965,"remaining_time":1.583157061},
{"learn":[0.08028384758],"iteration":891,"passed_time":12.95309229,"remaining_time":1.568311623},
{"learn":[0.08023848367],"iteration":892,"passed_time":12.96456491,"remaining_time":1.553424911},
{"learn":[0.08014318461],"iteration":893,"passed_time":12.97755527,"remaining_time":1.538725793},
{"learn":[0.08007203377],"iteration":894,"passed_time":12.99080067,"remaining_time":1.524060413},
{"learn":[0.08000979337],"iteration":895,"passed_time":13.0048332,"remaining_time":1.509489568},
{"learn":[0.07997799372],"iteration":896,"passed_time":13.01601916,"remaining_time":1.494593058},
{"learn":[0.0799287037],"iteration":897,"passed_time":13.02772681,"remaining_time":1.47976407},
{"learn":[0.07987231746],"iteration":898,"passed_time":13.04105149,"remaining_time":1.465123694},
{"learn":[0.07985532423],"iteration":899,"passed_time":13.0525424,"remaining_time":1.450282489},
{"learn":[0.07979486549],"iteration":900,"passed_time":13.06648465,"remaining_time":1.435718069},
{"learn":[0.07978835223],"iteration":901,"passed_time":13.0775242,"remaining_time":1.420839658},
{"learn":[0.07975635421],"iteration":902,"passed_time":13.09037977,"remaining_time":1.406164826},
{"learn":[0.07965149458],"iteration":903,"passed_time":13.10291089,"remaining_time":1.391459564},
{"learn":[0.07958696427],"iteration":904,"passed_time":13.11568918,"remaining_time":1.376785052},
{"learn":[0.07953254023],"iteration":905,"passed_time":13.12690259,"remaining_time":1.361952366},
{"learn":[0.0795038864],"iteration":906,"passed_time":13.13857458,"remaining_time":1.347174681},
{"learn":[0.07941520182],"iteration":907,"passed_time":13.15247008,"remaining_time":1.332629127},
{"learn":[0.07929335113],"iteration":908,"passed_time":13.16543535,"remaining_time":1.317991878},
{"learn":[0.0792667858],"iteration":909,"passed_time":13.17735046,"remaining_time":1.303254441},
{"learn":[0.07924205281],"iteration":910,"passed_time":13.18895107,"remaining_time":1.288492476},
{"learn":[0.07918826043],"iteration":911,"passed_time":13.20164115,"remaining_time":1.273842567},
{"learn":[0.07914943716],"iteration":912,"passed_time":13.21343467,"remaining_time":1.259111519},
{"learn":[0.07914774828],"iteration":913,"passed_time":13.22525778,"remaining_time":1.244389682},
{"learn":[0.07913664418],"iteration":914,"passed_time":13.23742083,"remaining_time":1.22970576},
{"learn":[0.07913291399],"iteration":915,"passed_time":13.24811906,"remaining_time":1.214893014},
{"learn":[0.07910425031],"iteration":916,"passed_time":13.25946052,"remaining_time":1.200147462},
{"learn":[0.07903592312],"iteration":917,"passed_time":13.27263141,"remaining_time":1.18557274},
{"learn":[0.07901208709],"iteration":918,"passed_time":13.2841819,"remaining_time":1.170858252},
{"learn":[0.07897761397],"iteration":919,"passed_time":13.29548186,"remaining_time":1.156128857},
{"learn":[0.0788978863],"iteration":920,"passed_time":13.30846905,"remaining_time":1.141551634},
{"learn":[0.07880047703],"iteration":921,"passed_time":13.32247329,"remaining_time":1.127063901},
{"learn":[0.07872730711],"iteration":922,"passed_time":13.33611192,"remaining_time":1.112546715},
{"learn":[0.07858620619],"iteration":923,"passed_time":13.34868359,"remaining_time":1.097943672},
{"learn":[0.07851717769],"iteration":924,"passed_time":13.36127417,"remaining_time":1.083346554},
{"learn":[0.07843512072],"iteration":925,"passed_time":13.37452381,"remaining_time":1.068806438},
{"learn":[0.0783450228],"iteration":926,"passed_time":13.38713668,"remaining_time":1.054218962},
{"learn":[0.07833236631],"iteration":927,"passed_time":13.39961243,"remaining_time":1.039625103},
{"learn":[0.07829282874],"iteration":928,"passed_time":13.41178986,"remaining_time":1.025013004},
{"learn":[0.07827053925],"iteration":929,"passed_time":13.42502867,"remaining_time":1.010486029},
{"learn":[0.07822191172],"iteration":930,"passed_time":13.43686265,"remaining_time":0.9958577047},
{"learn":[0.07818809478],"iteration":931,"passed_time":13.4500933,"remaining_time":0.9813372791},
{"learn":[0.07816343796],"iteration":932,"passed_time":13.46059966,"remaining_time":0.9666239838},
{"learn":[0.0781317146],"iteration":933,"passed_time":13.47374351,"remaining_time":0.9521060724},
{"learn":[0.07808962328],"iteration":934,"passed_time":13.48596306,"remaining_time":0.9375268438},
{"learn":[0.07808041477],"iteration":935,"passed_time":13.49715119,"remaining_time":0.9228821326},
{"learn":[0.07803742136],"iteration":936,"passed_time":13.51096944,"remaining_time":0.9084216377},
{"learn":[0.07800969192],"iteration":937,"passed_time":13.52225914,"remaining_time":0.8937953806},
{"learn":[0.0779147117],"iteration":938,"passed_time":13.53626347,"remaining_time":0.879352579},
{"learn":[0.07791358004],"iteration":939,"passed_time":13.54692716,"remaining_time":0.8646974781},
{"learn":[0.07783158561],"iteration":940,"passed_time":13.56031138,"remaining_time":0.850221436},
{"learn":[0.07777915461],"iteration":941,"passed_time":13.57261176,"remaining_time":0.8356809789},
{"learn":[0.07774462811],"iteration":942,"passed_time":13.58543442,"remaining_time":0.8211768418},
{"learn":[0.0776904318],"iteration":943,"passed_time":13.59718378,"remaining_time":0.8066125969},
{"learn":[0.07764749783],"iteration":944,"passed_time":13.60935008,"remaining_time":0.7920785761},
{"learn":[0.07763798749],"iteration":945,"passed_time":13.62142822,"remaining_time":0.7775445284},
{"learn":[0.07758289747],"iteration":946,"passed_time":13.634186,"remaining_time":0.7630537045},
{"learn":[0.07749983035],"iteration":947,"passed_time":13.64686937,"remaining_time":0.748562455},
{"learn":[0.07743806177],"iteration":948,"passed_time":13.65909955,"remaining_time":0.7340506607},
{"learn":[0.0773247871],"iteration":949,"passed_time":13.67136552,"remaining_time":0.7195455535},
{"learn":[0.07730399324],"iteration":950,"passed_time":13.68335949,"remaining_time":0.705031141},
{"learn":[0.07724949953],"iteration":951,"passed_time":13.69621481,"remaining_time":0.6905654528},
{"learn":[0.07719604833],"iteration":952,"passed_time":13.7099594,"remaining_time":0.6761470007},
{"learn":[0.07718214714],"iteration":953,"passed_time":13.72259914,"remaining_time":0.6616766883},
{"learn":[0.07714374432],"iteration":954,"passed_time":13.7349159,"remaining_time":0.6471949901},
{"learn":[0.07707786958],"iteration":955,"passed_time":13.74821425,"remaining_time":0.632762999},
{"learn":[0.07707207084],"iteration":956,"passed_time":13.75943096,"remaining_time":0.6182398446},
{"learn":[0.07697343814],"iteration":957,"passed_time":13.77265564,"remaining_time":0.6038116253},
{"learn":[0.07690535791],"iteration":958,"passed_time":13.78607066,"remaining_time":0.5893940531},
{"learn":[0.0768542482],"iteration":959,"passed_time":13.79843995,"remaining_time":0.5749349981},
{"learn":[0.07683278247],"iteration":960,"passed_time":13.80980028,"remaining_time":0.5604393455},
{"learn":[0.07682103321],"iteration":961,"passed_time":13.82221491,"remaining_time":0.5459918572},
{"learn":[0.07675843309],"iteration":962,"passed_time":13.83417668,"remaining_time":0.5315311913},
{"learn":[0.0767143939],"iteration":963,"passed_time":13.8474989,"remaining_time":0.5171265151},
{"learn":[0.07663214942],"iteration":964,"passed_time":13.86055255,"remaining_time":0.5027143413},
{"learn":[0.07658816745],"iteration":965,"passed_time":13.87319322,"remaining_time":0.4882904444},
{"learn":[0.07648117357],"iteration":966,"passed_time":13.88717917,"remaining_time":0.4739161453},
{"learn":[0.07638596854],"iteration":967,"passed_time":13.90109641,"remaining_time":0.4595403773},
{"learn":[0.07631674745],"iteration":968,"passed_time":13.91328184,"remaining_time":0.4451101517},
{"learn":[0.07622536597],"iteration":969,"passed_time":13.92559389,"remaining_time":0.4306884708},
{"learn":[0.07615130076],"iteration":970,"passed_time":13.93782498,"remaining_time":0.4162687173},
{"learn":[0.0760766204],"iteration":971,"passed_time":13.95365937,"remaining_time":0.4019572658},
{"learn":[0.07602410595],"iteration":972,"passed_time":13.96601275,"remaining_time":0.3875460887},
{"learn":[0.07596014104],"iteration":973,"passed_time":13.97930323,"remaining_time":0.3731641518},
{"learn":[0.07593696852],"iteration":974,"passed_time":13.98986412,"remaining_time":0.3587144647},
{"learn":[0.07585125877],"iteration":975,"passed_time":14.00271965,"remaining_time":0.3443291718},
{"learn":[0.07581453747],"iteration":976,"passed_time":14.01536269,"remaining_time":0.3299420081},
{"learn":[0.0757181108],"iteration":977,"passed_time":14.04113758,"remaining_time":0.3158538107},
{"learn":[0.07563634754],"iteration":978,"passed_time":14.05352121,"remaining_time":0.3014544898},
{"learn":[0.07563190949],"iteration":979,"passed_time":14.06570081,"remaining_time":0.2870551185},
{"learn":[0.07557525349],"iteration":980,"passed_time":14.07775724,"remaining_time":0.2726578874},
{"learn":[0.07548054976],"iteration":981,"passed_time":14.09184256,"remaining_time":0.2583026132},
{"learn":[0.07546300668],"iteration":982,"passed_time":14.10442585,"remaining_time":0.243921912},
{"learn":[0.07539313518],"iteration":983,"passed_time":14.11700489,"remaining_time":0.229544795},
{"learn":[0.07530260564],"iteration":984,"passed_time":14.13020412,"remaining_time":0.2151807734},
{"learn":[0.07524186659],"iteration":985,"passed_time":14.14378796,"remaining_time":0.2008245755},
{"learn":[0.0751941539],"iteration":986,"passed_time":14.15641804,"remaining_time":0.1864573805},
{"learn":[0.07510637095],"iteration":987,"passed_time":14.16938552,"remaining_time":0.1720977999},
{"learn":[0.07505391414],"iteration":988,"passed_time":14.18288445,"remaining_time":0.1577469454},
{"learn":[0.07502371776],"iteration":989,"passed_time":14.19435769,"remaining_time":0.1433773504},
{"learn":[0.07498742391],"iteration":990,"passed_time":14.20746617,"remaining_time":0.1290284516},
{"learn":[0.07491377382],"iteration":991,"passed_time":14.21948719,"remaining_time":0.1146732838},
{"learn":[0.07485814072],"iteration":992,"passed_time":14.23289854,"remaining_time":0.1003326181},
{"learn":[0.07480971042],"iteration":993,"passed_time":14.24480406,"remaining_time":0.08598473274},
{"learn":[0.07474596174],"iteration":994,"passed_time":14.25746247,"remaining_time":0.07164554004},
{"learn":[0.0746889696],"iteration":995,"passed_time":14.26858322,"remaining_time":0.05730354708},
{"learn":[0.07468055136],"iteration":996,"passed_time":14.28103752,"remaining_time":0.04297202864},
{"learn":[0.07462104583],"iteration":997,"passed_time":14.29289166,"remaining_time":0.02864306947},
{"learn":[0.0745749324],"iteration":998,"passed_time":14.30567736,"remaining_time":0.01431999736},
{"learn":[0.07450361331],"iteration":999,"passed_time":14.31727648,"remaining_time":0}
]}